{
  "resourceType" : "CodeSystem",
  "id" : "67ed97a3-4854-498f-be9e-2d9efbf4cafd-288",
  "url" : "http://hl7.org/fhir/comparison/CodeSystem/67ed97a3-4854-498f-be9e-2d9efbf4cafd-288",
  "name" : "IntersectionTRE_R249-SexeAndTRE_R249-Sexe",
  "title" : "Intersection of null And null",
  "status" : "active",
  "date" : "2024-11-03T10:18:59+00:00",
  "property" : [{
    "code" : "dateValid",
    "description" : "date de validité d'un code concept",
    "type" : "dateTime"
  },
  {
    "code" : "dateMaj",
    "description" : "Date de mise à jour d'un code concept",
    "type" : "dateTime"
  },
  {
    "code" : "dateFin",
    "description" : "Date de fin d'exploitation d'un code concept",
    "type" : "dateTime"
  },
  {
    "code" : "dateValid",
    "description" : "date de validité d'un code concept",
    "type" : "dateTime"
  },
  {
    "code" : "dateMaj",
    "description" : "Date de mise à jour d'un code concept",
    "type" : "dateTime"
  },
  {
    "code" : "dateFin",
    "description" : "Date de fin d'exploitation d'un code concept",
    "type" : "dateTime"
  }],
  "concept" : [{
    "code" : "U",
    "display" : "Inconnu",
    "designation" : [{
      "use" : {
        "code" : "LibelleCourt"
      },
      "value" : "Inconnu"
    },
    {
      "use" : {
        "code" : "LibelleAdapte"
      },
      "value" : "Inconnu"
    }],
    "property" : [{
      "code" : "dateValid",
      "valueDateTime" : "2018-01-26T12:00:00+01:00"
    },
    {
      "code" : "dateFin",
      "valueDateTime" : "2023-12-15T12:00:00+01:00"
    },
    {
      "code" : "dateMaj",
      "valueDateTime" : "2023-12-15T12:00:00+01:00"
    },
    {
      "code" : "dateValid",
      "valueDateTime" : "2018-01-26T12:00:00+01:00"
    },
    {
      "code" : "dateFin",
      "valueDateTime" : "2023-12-15T12:00:00+01:00"
    },
    {
      "code" : "dateMaj",
      "valueDateTime" : "2023-12-15T12:00:00+01:00"
    }]
  },
  {
    "code" : "UN",
    "display" : "Inconnu",
    "designation" : [{
      "use" : {
        "code" : "LibelleCourt"
      },
      "value" : "Inconnu"
    },
    {
      "use" : {
        "code" : "LibelleAdapte"
      },
      "value" : "Inconnu"
    }],
    "property" : [{
      "code" : "dateValid",
      "valueDateTime" : "2023-12-15T12:00:00+01:00"
    },
    {
      "code" : "dateMaj",
      "valueDateTime" : "2023-12-15T12:00:00+01:00"
    },
    {
      "code" : "dateValid",
      "valueDateTime" : "2023-12-15T12:00:00+01:00"
    },
    {
      "code" : "dateMaj",
      "valueDateTime" : "2023-12-15T12:00:00+01:00"
    }]
  },
  {
    "code" : "F",
    "display" : "Féminin",
    "designation" : [{
      "use" : {
        "code" : "LibelleCourt"
      },
      "value" : "Féminin"
    },
    {
      "use" : {
        "code" : "LibelleAdapte"
      },
      "value" : "Féminin"
    }],
    "property" : [{
      "code" : "dateValid",
      "valueDateTime" : "2018-01-26T12:00:00+01:00"
    },
    {
      "code" : "dateMaj",
      "valueDateTime" : "2018-01-26T12:00:00+01:00"
    },
    {
      "code" : "dateValid",
      "valueDateTime" : "2018-01-26T12:00:00+01:00"
    },
    {
      "code" : "dateMaj",
      "valueDateTime" : "2018-01-26T12:00:00+01:00"
    }]
  },
  {
    "code" : "M",
    "display" : "Masculin",
    "designation" : [{
      "use" : {
        "code" : "LibelleCourt"
      },
      "value" : "Masculin"
    },
    {
      "use" : {
        "code" : "LibelleAdapte"
      },
      "value" : "Masculin"
    }],
    "property" : [{
      "code" : "dateValid",
      "valueDateTime" : "2018-01-26T12:00:00+01:00"
    },
    {
      "code" : "dateMaj",
      "valueDateTime" : "2018-01-26T12:00:00+01:00"
    },
    {
      "code" : "dateValid",
      "valueDateTime" : "2018-01-26T12:00:00+01:00"
    },
    {
      "code" : "dateMaj",
      "valueDateTime" : "2018-01-26T12:00:00+01:00"
    }]
  },
  {
    "code" : "O",
    "display" : "Autre sexe (ni masculin, ni féminin)",
    "designation" : [{
      "use" : {
        "code" : "LibelleCourt"
      },
      "value" : "Autre sexe ni M, ni F"
    },
    {
      "use" : {
        "code" : "LibelleAdapte"
      },
      "value" : "Autre sexe (ni masculin, ni féminin)"
    }],
    "property" : [{
      "code" : "dateValid",
      "valueDateTime" : "2018-02-28T12:00:00+01:00"
    },
    {
      "code" : "dateMaj",
      "valueDateTime" : "2018-12-14T12:00:00+01:00"
    },
    {
      "code" : "dateValid",
      "valueDateTime" : "2018-02-28T12:00:00+01:00"
    },
    {
      "code" : "dateMaj",
      "valueDateTime" : "2018-12-14T12:00:00+01:00"
    }]
  }]
}