{
  "resourceType" : "ValueSet",
  "id" : "ead9e332-1c5a-4b5c-9081-6ee054fca83e-1337",
  "url" : "http://hl7.org/fhir/comparison/ValueSet/ead9e332-1c5a-4b5c-9081-6ee054fca83e-1337",
  "name" : "UnionJDV_J50-AccessibiliteLieu-RORAndJDV_J50-AccessibiliteLieu-ROR",
  "title" : "Union of null And null",
  "status" : "active",
  "date" : "2024-11-04T04:21:23+00:00",
  "compose" : {
    "include" : [{
      "concept" : [{
        "code" : "1",
        "display" : "Accessible"
      },
      {
        "code" : "2",
        "display" : "Non accessible"
      },
      {
        "code" : "3",
        "display" : "Sur demande"
      },
      {
        "code" : "4",
        "display" : "Non communiqué"
      },
      {
        "code" : "5",
        "display" : "Conforme"
      },
      {
        "code" : "6",
        "display" : "Ad'AP"
      }]
    }]
  }
}