{
  "resourceType" : "ValueSet",
  "id" : "9c375d00-e288-49fe-95e9-cf72720e9d41-975",
  "url" : "http://hl7.org/fhir/comparison/ValueSet/9c375d00-e288-49fe-95e9-cf72720e9d41-975",
  "name" : "IntersectionJDV_J166-Profession-EPARSAndJDV_J166-Profession-EPARS",
  "title" : "Intersection of null And null",
  "status" : "active",
  "date" : "2024-10-26T10:18:40+00:00",
  "compose" : {
    "include" : [{
      "concept" : [{
        "code" : "26",
        "display" : "Audioprothésiste"
      },
      {
        "code" : "28",
        "display" : "Opticien-Lunetier"
      },
      {
        "code" : "31",
        "display" : "Assistant dentaire"
      },
      {
        "code" : "32",
        "display" : "Physicien médical"
      }]
    },
    {
      "concept" : [{
        "code" : "41",
        "display" : "Assistant de service social"
      }]
    },
    {
      "concept" : [{
        "code" : "71",
        "display" : "Ostéopathe"
      },
      {
        "code" : "72",
        "display" : "Psychothérapeute"
      },
      {
        "code" : "73",
        "display" : "Chiropracteur"
      }]
    },
    {
      "concept" : [{
        "code" : "81",
        "display" : "Orthoprothésiste"
      },
      {
        "code" : "82",
        "display" : "Podo-Orthésiste"
      },
      {
        "code" : "83",
        "display" : "Orthopédiste-Orthésiste"
      },
      {
        "code" : "84",
        "display" : "Oculariste"
      },
      {
        "code" : "85",
        "display" : "Epithésiste"
      },
      {
        "code" : "86",
        "display" : "Technicien de laboratoire médical"
      },
      {
        "code" : "91",
        "display" : "Orthophoniste"
      },
      {
        "code" : "92",
        "display" : "Orthoptiste"
      }]
    },
    {
      "concept" : [{
        "code" : "93",
        "display" : "Psychologue"
      }]
    },
    {
      "concept" : [{
        "code" : "94",
        "display" : "Ergothérapeute"
      },
      {
        "code" : "95",
        "display" : "Diététicien"
      },
      {
        "code" : "96",
        "display" : "Psychomotricien"
      }]
    },
    {
      "concept" : [{
        "code" : "97",
        "display" : "Conseiller en génétique"
      }]
    },
    {
      "concept" : [{
        "code" : "98",
        "display" : "Manipulateur ERM"
      }]
    }]
  }
}