{
  "resourceType" : "ValueSet",
  "id" : "b337eee2-05ca-495e-bb2d-9a6e2e65efde-1062",
  "url" : "http://hl7.org/fhir/comparison/ValueSet/b337eee2-05ca-495e-bb2d-9a6e2e65efde-1062",
  "name" : "IntersectionJDV_J195-AffectationTemporaire-RORAndJDV_J195-AffectationTemporaire-ROR",
  "title" : "Intersection of null And null",
  "status" : "active",
  "date" : "2024-10-31T15:18:00+00:00",
  "compose" : {
    "include" : [{
      "concept" : [{
        "code" : "01",
        "display" : "Aucune"
      },
      {
        "code" : "02",
        "display" : "Covid+"
      },
      {
        "code" : "03",
        "display" : "Covid-"
      }]
    }]
  }
}