{
  "resourceType" : "ValueSet",
  "id" : "503e4c32-d535-4e7a-ad1f-bbaaf596b8b5-863",
  "url" : "http://hl7.org/fhir/comparison/ValueSet/503e4c32-d535-4e7a-ad1f-bbaaf596b8b5-863",
  "name" : "UnionJDV_J130-CNAMAmeliSecteurConventionnement-RASSAndJDV_J130-CNAMAmeliSecteurConventionnement-RASS",
  "title" : "Union of null And null",
  "status" : "active",
  "date" : "2024-10-27T10:16:11+00:00",
  "compose" : {
    "include" : [{
      "concept" : [{
        "code" : "nc",
        "display" : "Non conventionné"
      },
      {
        "code" : "c1",
        "display" : "Secteur 1 ou conventionné"
      },
      {
        "code" : "c2",
        "display" : "Secteur 1 ou conventionné avec droit au dépassement permanent"
      },
      {
        "code" : "c3",
        "display" : "Secteur 2"
      }]
    }]
  }
}