{
  "resourceType" : "ValueSet",
  "id" : "b6732388-b060-4718-bc22-b934b86840a0-1209",
  "url" : "http://hl7.org/fhir/comparison/ValueSet/b6732388-b060-4718-bc22-b934b86840a0-1209",
  "name" : "IntersectionJDV_J241-ThematiqueAnomalie-RORAndJDV_J241-ThematiqueAnomalie-ROR",
  "title" : "Intersection of null And null",
  "status" : "active",
  "date" : "2024-10-24T04:20:33+00:00",
  "compose" : {
    "include" : [{
      "concept" : [{
        "code" : "01",
        "display" : "Complétude"
      },
      {
        "code" : "02",
        "display" : "Exhaustivité"
      },
      {
        "code" : "03",
        "display" : "Cohérence"
      },
      {
        "code" : "04",
        "display" : "Récence"
      },
      {
        "code" : "05",
        "display" : "Structuration"
      },
      {
        "code" : "06",
        "display" : "Exactitude"
      }]
    }]
  }
}