{
  "resourceType" : "ValueSet",
  "id" : "beb7d624-a683-4307-a61f-e69a6fe3da60-773",
  "url" : "http://hl7.org/fhir/comparison/ValueSet/beb7d624-a683-4307-a61f-e69a6fe3da60-773",
  "name" : "UnionJDV_J08-XdsConfidentialityCode-CISISAndJDV_J08-XdsConfidentialityCode-CISIS",
  "title" : "Union of null And null",
  "status" : "active",
  "date" : "2024-11-07T10:18:45+00:00",
  "compose" : {
    "include" : [{
      "concept" : [{
        "code" : "N",
        "display" : "Normal"
      },
      {
        "code" : "R",
        "display" : "Restreint"
      },
      {
        "code" : "V",
        "display" : "Très restreint"
      }]
    },
    {
      "concept" : [{
        "code" : "INVISIBLE_PATIENT",
        "display" : "Non visible par le patient"
      },
      {
        "code" : "INVISIBLE_REPRESENTANTS_LEGAUX",
        "display" : "Non visible par les représentants légaux du patient"
      },
      {
        "code" : "MASQUE_PS",
        "display" : "Masqué aux professionnels de santé"
      }]
    }]
  }
}