{
  "resourceType" : "ValueSet",
  "id" : "01bffc5c-527d-4d21-ad7d-c8319265a01b-1320",
  "url" : "http://hl7.org/fhir/comparison/ValueSet/01bffc5c-527d-4d21-ad7d-c8319265a01b-1320",
  "name" : "IntersectionJDV_J41-TypeHoraire-RORAndJDV_J41-TypeHoraire-ROR",
  "title" : "Intersection of null And null",
  "status" : "active",
  "date" : "2024-10-30T15:18:01+00:00",
  "compose" : {
    "include" : [{
      "concept" : [{
        "code" : "01",
        "display" : "Horaire d'ouverture"
      },
      {
        "code" : "02",
        "display" : "Horaire de fonctionnement"
      },
      {
        "code" : "03",
        "display" : "Horaire de garde"
      },
      {
        "code" : "04",
        "display" : "Horaire d'ouverture du secrétariat"
      },
      {
        "code" : "05",
        "display" : "Horaire de visite à domicile"
      },
      {
        "code" : "06",
        "display" : "Horaire de consultation sans RDV"
      },
      {
        "code" : "07",
        "display" : "Horaire de consultation sur RDV"
      },
      {
        "code" : "08",
        "display" : "Horaire de fermeture"
      },
      {
        "code" : "09",
        "display" : "Horaire à préciser"
      }]
    }]
  }
}