{
  "resourceType" : "ValueSet",
  "id" : "27f0cd77-137b-40f3-bc3b-bb1096df0e13-959",
  "url" : "http://hl7.org/fhir/comparison/ValueSet/27f0cd77-137b-40f3-bc3b-bb1096df0e13-959",
  "name" : "UnionJDV_J161-Lateralite-CISISAndJDV_J161-Lateralite-CISIS",
  "title" : "Union of null And null",
  "status" : "active",
  "date" : "2024-11-04T10:19:23+00:00",
  "compose" : {
    "include" : [{
      "concept" : [{
        "code" : "24028007",
        "display" : "côté droit"
      },
      {
        "code" : "7771000",
        "display" : "côté gauche"
      },
      {
        "code" : "51440002",
        "display" : "bilatéral(e)"
      },
      {
        "code" : "385432009",
        "display" : "non applicable"
      }]
    }]
  }
}