{
  "resourceType" : "ValueSet",
  "id" : "33610c1d-51c2-473c-90db-dc7b63d7a3a1-935",
  "url" : "http://hl7.org/fhir/comparison/ValueSet/33610c1d-51c2-473c-90db-dc7b63d7a3a1-935",
  "name" : "UnionJDV_J153-TypeDiabete-ENSAndJDV_J153-TypeDiabete-ENS",
  "title" : "Union of null And null",
  "status" : "active",
  "date" : "2024-10-23T04:19:54+00:00",
  "compose" : {
    "include" : [{
      "concept" : [{
        "code" : "E11.x0",
        "display" : "Diabète type 2 insulinotraité"
      },
      {
        "code" : "E11.x8",
        "display" : "Diabète type 2 non insulinotraité"
      }]
    },
    {
      "concept" : [{
        "code" : "E10",
        "display" : "Diabète sucré de type 1"
      },
      {
        "code" : "O24.4",
        "display" : "Diabète sucré survenant au cours de la grossesse"
      },
      {
        "code" : "E14",
        "display" : "Diabète sucré, sans précision"
      }]
    },
    {
      "concept" : [{
        "code" : "MED-874",
        "display" : "Non diabétique"
      }]
    }]
  }
}