{
  "resourceType" : "ValueSet",
  "id" : "f0622d35-8af1-4822-acf3-0f850cdf7fef-909",
  "url" : "http://hl7.org/fhir/comparison/ValueSet/f0622d35-8af1-4822-acf3-0f850cdf7fef-909",
  "name" : "IntersectionJDV_J144-ParticipationType-CISISAndJDV_J144-ParticipationType-CISIS",
  "title" : "Intersection of null And null",
  "status" : "active",
  "date" : "2024-11-03T15:16:19+00:00",
  "compose" : {
    "include" : [{
      "concept" : [{
        "code" : "REF",
        "display" : "Référent / Prescripteur"
      },
      {
        "code" : "REFB",
        "display" : "Personne ayant adressé le patient"
      },
      {
        "code" : "INF",
        "display" : "Informateur"
      },
      {
        "code" : "RESP",
        "display" : "Responsable de l'acte"
      },
      {
        "code" : "PRF",
        "display" : "Exécutant"
      },
      {
        "code" : "CON",
        "display" : "Consultant"
      },
      {
        "code" : "VRF",
        "display" : "Vérificateur"
      }]
    }]
  }
}