{
  "resourceType" : "ValueSet",
  "id" : "f0622d35-8af1-4822-acf3-0f850cdf7fef-1088",
  "url" : "http://hl7.org/fhir/comparison/ValueSet/f0622d35-8af1-4822-acf3-0f850cdf7fef-1088",
  "name" : "UnionJDV_J203-TypeOrganisationInterne-RORAndJDV_J203-TypeOrganisationInterne-ROR",
  "title" : "Union of null And null",
  "status" : "active",
  "date" : "2024-11-03T15:16:19+00:00",
  "compose" : {
    "include" : [{
      "concept" : [{
        "code" : "1",
        "display" : "Pôle"
      },
      {
        "code" : "2",
        "display" : "Structure interne ou Service"
      },
      {
        "code" : "3",
        "display" : "Unité fonctionnelle"
      },
      {
        "code" : "4",
        "display" : "Unité élémentaire"
      }]
    },
    {
      "concept" : [{
        "code" : "EJ",
        "display" : "Entité juridique"
      },
      {
        "code" : "EG",
        "display" : "Etablissement géographique"
      }]
    }]
  }
}