<?xml version="1.0" encoding="UTF-8" standalone="no"?>
<RetrieveValueSetResponse xmlns="urn:ihe:iti:svs:2008" xmlns:xsi="http://www.w3.org/2001/XMLSchema-instance">
    <ValueSet dateFin="" dateMaj="20250228120000" dateValid="19790101000000" description="Catégorie d'établissements" displayName="TRE_R66-CategorieEtablissement.tabs" id="1.2.250.1.213.1.6.1.8" typeFichier="TRE" urlFichier="https://mos.esante.gouv.fr/NOS/TRE_R66-CategorieEtablissement">
        <ConceptList>
            <Concept code="001" codeSystem="1.2.250.1.213.1.6.1.8" dateFin="19990915000000" dateMaj="19990915000000" dateValid="19790101000000" displayName="Autres lits de mR" longDesignation="Autres lits de m.R." shortDesignation="Autres lits de m.R."/>
            <Concept code="002" codeSystem="1.2.250.1.213.1.6.1.8" dateFin="19990915000000" dateMaj="19990915000000" dateValid="19790101000000" displayName="Autres places de l-f" longDesignation="Autres places de l-f." shortDesignation="Autres places de l-f"/>
            <Concept code="003" codeSystem="1.2.250.1.213.1.6.1.8" dateFin="19990915000000" dateMaj="19990915000000" dateValid="19790101000000" displayName="Autres lits de l-s" longDesignation="Autres lits de l-s" shortDesignation="Autres lits de l-s"/>
            <Concept code="101" codeSystem="1.2.250.1.213.1.6.1.8" dateFin="" dateMaj="19900105000000" dateValid="19790101000000" displayName="Centre hospitalier régional (CHR)" longDesignation="Centre Hospitalier Régional (C.H.R.)" shortDesignation="C.H.R."/>
            <Concept code="106" codeSystem="1.2.250.1.213.1.6.1.8" dateFin="" dateMaj="20120111000000" dateValid="19790101000000" displayName="Centre hospitalier (ex Hôpital local)" longDesignation="Centre hospitalier, ex Hôpital local" shortDesignation="C.H. (ex H.L.)"/>
            <Concept code="108" codeSystem="1.2.250.1.213.1.6.1.8" dateFin="20130625000000" dateMaj="19940705000000" dateValid="19790101000000" displayName="Etablissement de convalescence et de repos" longDesignation="Etablissement de Convalescence et de Repos" shortDesignation="Etab.Convales.&amp;Repos"/>
            <Concept code="109" codeSystem="1.2.250.1.213.1.6.1.8" dateFin="" dateMaj="20130625000000" dateValid="20130625000000" displayName="Etablissement de santé privé autorisé en soins de suite et de réadaptation (SSR)" longDesignation="Etablissement de santé privé autorisé en SSR" shortDesignation="Soins suite réadap"/>
            <Concept code="112" codeSystem="1.2.250.1.213.1.6.1.8" dateFin="19990915000000" dateMaj="19990915000000" dateValid="19790101000000" displayName="Centre de convalescence, de cure ou de réadaptation" longDesignation="Centre de Convalescence Cure ou Réadaptation" shortDesignation="Ctre.Conval.Cure Réa"/>
            <Concept code="114" codeSystem="1.2.250.1.213.1.6.1.8" dateFin="" dateMaj="19990915000000" dateValid="19790101000000" displayName="Hôpital des armées" longDesignation="Hôpital des armées" shortDesignation="Hôpital armées"/>
            <Concept code="115" codeSystem="1.2.250.1.213.1.6.1.8" dateFin="" dateMaj="19990915000000" dateValid="19790101000000" displayName="Etablissement de soins du Service de santé des armées (SSA)" longDesignation="Etablissement de Soins du Service de Santé des Armées" shortDesignation="Etab.Soins Armées"/>
            <Concept code="119" codeSystem="1.2.250.1.213.1.6.1.8" dateFin="20130625000000" dateMaj="19790123000000" dateValid="19790101000000" displayName="Maison de régime" longDesignation="Maison de Régime" shortDesignation="Maison de Régime"/>
            <Concept code="122" codeSystem="1.2.250.1.213.1.6.1.8" dateFin="" dateMaj="19940707000000" dateValid="19790101000000" displayName="Etablissement de soins obstétriques et chirurgico-gynécologiques" longDesignation="Etablissement Soins Obstétriques Chirurgico-Gynécologiques" shortDesignation="Etab.Obs.Chir.Gynéco"/>
            <Concept code="124" codeSystem="1.2.250.1.213.1.6.1.8" dateFin="" dateMaj="20131219000000" dateValid="20131219000000" displayName="Centre de santé" longDesignation="Centre de Santé" shortDesignation="Centre de Santé"/>
            <Concept code="125" codeSystem="1.2.250.1.213.1.6.1.8" dateFin="20131219000000" dateMaj="20131219000000" dateValid="19790101000000" displayName="Centre de santé dentaire" longDesignation="Centre de Santé Dentaire" shortDesignation="Ctre.Santé Dentaire"/>
            <Concept code="126" codeSystem="1.2.250.1.213.1.6.1.8" dateFin="" dateMaj="19910301000000" dateValid="19790101000000" displayName="Etablissement thermal" longDesignation="Etablissement Thermal" shortDesignation="Etab.Thermal"/>
            <Concept code="127" codeSystem="1.2.250.1.213.1.6.1.8" dateFin="" dateMaj="19940708000000" dateValid="19790101000000" displayName="Hospitalisation à domicile (HAD)" longDesignation="Hospitalisation à Domicile" shortDesignation="Hosp.à Domicile"/>
            <Concept code="128" codeSystem="1.2.250.1.213.1.6.1.8" dateFin="" dateMaj="19940705000000" dateValid="19790101000000" displayName="Etablissement de soins chirurgicaux" longDesignation="Etablissement de Soins Chirurgicaux" shortDesignation="Etab.Soins Chirur."/>
            <Concept code="129" codeSystem="1.2.250.1.213.1.6.1.8" dateFin="" dateMaj="19940705000000" dateValid="19790101000000" displayName="Etablissement de soins médicaux" longDesignation="Etablissement de Soins Médicaux" shortDesignation="Etab.Soins Médicaux"/>
            <Concept code="130" codeSystem="1.2.250.1.213.1.6.1.8" dateFin="20131219000000" dateMaj="20131219000000" dateValid="19790101000000" displayName="Centre de soins médicaux" longDesignation="Centre de Soins Médicaux" shortDesignation="Ctre.Soins Médicaux"/>
            <Concept code="131" codeSystem="1.2.250.1.213.1.6.1.8" dateFin="" dateMaj="19790123000000" dateValid="19790101000000" displayName="Centre de lutte contre cancer" longDesignation="Centre de Lutte Contre Cancer" shortDesignation="Ctre.Lutte C.Cancer"/>
            <Concept code="132" codeSystem="1.2.250.1.213.1.6.1.8" dateFin="" dateMaj="19940705000000" dateValid="19790101000000" displayName="Etablissement de transfusion sanguine" longDesignation="Etablissement de Transfusion Sanguine" shortDesignation="Etab.Trans.Sanguine"/>
            <Concept code="135" codeSystem="1.2.250.1.213.1.6.1.8" dateFin="20130625000000" dateMaj="19940705000000" dateValid="19790101000000" displayName="Etablissement réadaptation fonctionnelle" longDesignation="Etablissement Réadaptation Fonctionnelle" shortDesignation="Etab.Réadap.Fonct."/>
            <Concept code="136" codeSystem="1.2.250.1.213.1.6.1.8" dateFin="19990915000000" dateMaj="19990915000000" dateValid="19790101000000" displayName="Banque de sperme" longDesignation="Banque de Sperme" shortDesignation="Banque de Sperme"/>
            <Concept code="137" codeSystem="1.2.250.1.213.1.6.1.8" dateFin="19990915000000" dateMaj="19990915000000" dateValid="19790101000000" displayName="Banque d'organes" longDesignation="Banque d'Organes" shortDesignation="Banque d'Organes"/>
            <Concept code="138" codeSystem="1.2.250.1.213.1.6.1.8" dateFin="20020218000000" dateMaj="20020218000000" dateValid="19790101000000" displayName="Centre de dialyse périodique" longDesignation="Centre de Dialyse Périodique" shortDesignation="Ctre.Dialyse Périod."/>
            <Concept code="139" codeSystem="1.2.250.1.213.1.6.1.8" dateFin="20020218000000" dateMaj="20020218000000" dateValid="19790101000000" displayName="Centre de dialyse et d'entraînement à la dialyse" longDesignation="Centre de Dialyse et d'entraînement à la Dialyse" shortDesignation="Ctre.Dial.Entr.Dial."/>
            <Concept code="140" codeSystem="1.2.250.1.213.1.6.1.8" dateFin="20020218000000" dateMaj="20020218000000" dateValid="19790101000000" displayName="Centre d'entraînement à la dialyse" longDesignation="Centre d'Entraînement à la Dialyse" shortDesignation="Ctre.Entrain.Dialyse"/>
            <Concept code="141" codeSystem="1.2.250.1.213.1.6.1.8" dateFin="" dateMaj="20020218000000" dateValid="20011001000000" displayName="Centre de dialyse" longDesignation="Centre de dialyse" shortDesignation="Ctre.Dialyse"/>
            <Concept code="142" codeSystem="1.2.250.1.213.1.6.1.8" dateFin="" dateMaj="19830720000000" dateValid="19790101000000" displayName="Dispensaire antituberculeux" longDesignation="Dispensaire Antituberculeux" shortDesignation="Disp.Anti-Tubercul."/>
            <Concept code="143" codeSystem="1.2.250.1.213.1.6.1.8" dateFin="" dateMaj="19891229000000" dateValid="19790101000000" displayName="Centre de vaccination BCG" longDesignation="Centre de Vaccination BCG" shortDesignation="Ctre.Vaccination BCG"/>
            <Concept code="144" codeSystem="1.2.250.1.213.1.6.1.8" dateFin="20130625000000" dateMaj="19910301000000" dateValid="19790101000000" displayName="Etablissement de lutte contre la tuberculose" longDesignation="Etablissement de Lutte Contre la Tuberculose" shortDesignation="Etab.Lutte Tubercul."/>
            <Concept code="146" codeSystem="1.2.250.1.213.1.6.1.8" dateFin="" dateMaj="20020218000000" dateValid="19790101000000" displayName="Structure d'alternative à la dialyse en centre" longDesignation="Structure d'Alternative à la dialyse en centre" shortDesignation="Alternative dialyse"/>
            <Concept code="156" codeSystem="1.2.250.1.213.1.6.1.8" dateFin="" dateMaj="19971119000000" dateValid="19790101000000" displayName="Centre médico-psychologique (CMP)" longDesignation="Centre Médico-Psychologique (C.M.P.)" shortDesignation="C.M.P."/>
            <Concept code="157" codeSystem="1.2.250.1.213.1.6.1.8" dateFin="19940919000000" dateMaj="19910301000000" dateValid="19790101000000" displayName="Centre de postcure" longDesignation="Centre de Postcure" shortDesignation="Ctre.de Postcure"/>
            <Concept code="159" codeSystem="1.2.250.1.213.1.6.1.8" dateFin="" dateMaj="20200626120000" dateValid="20200626120000" displayName="Centre Parental" longDesignation="Centre Parental" shortDesignation="Centre parental"/>
            <Concept code="160" codeSystem="1.2.250.1.213.1.6.1.8" dateFin="20121231000000" dateMaj="20130510000000" dateValid="19790101000000" displayName="Centre de soins spécifiques pour toxicomanes (CSST)" longDesignation="Centre de Soins Spécifiques pour Toxicomanes (C.S.S.T.)" shortDesignation="C.S.S.T."/>
            <Concept code="161" codeSystem="1.2.250.1.213.1.6.1.8" dateFin="" dateMaj="19790123000000" dateValid="19790101000000" displayName="Maison de santé pour maladies mentales" longDesignation="Maison de Santé pour Maladies Mentales" shortDesignation="Mais.Santé Mal.Ment"/>
            <Concept code="162" codeSystem="1.2.250.1.213.1.6.1.8" dateFin="20121231000000" dateMaj="20130510000000" dateValid="19790101000000" displayName="Centre de cure ambulatoire en alcoologie (CCAA)" longDesignation="Centre de Cure Ambulatoire en Alcoologie (C.C.A.A.)" shortDesignation="C.C.A.A."/>
            <Concept code="163" codeSystem="1.2.250.1.213.1.6.1.8" dateFin="20130625000000" dateMaj="19940705000000" dateValid="19790101000000" displayName="Maison d'enfants à caractère sanitaire (MECS) temporaire" longDesignation="Maison d'Enfants à Caractère Sanitaire Temporaire" shortDesignation="M.E.C.S. Temporaire"/>
            <Concept code="164" codeSystem="1.2.250.1.213.1.6.1.8" dateFin="20140331000000" dateMaj="20140331000000" dateValid="20000801000000" displayName="Etablissement expérimental d'accueil de la petite enfance" longDesignation="Etablissements Expérimentaux Accueil de la Petite Enfance" shortDesignation="Etab.exp.petite enf."/>
            <Concept code="165" codeSystem="1.2.250.1.213.1.6.1.8" dateFin="" dateMaj="20050706000000" dateValid="20020102000000" displayName="Appartement de coordination thérapeutique (ACT)" longDesignation="Appartement de Coordination Thérapeutique (A.C.T.)" shortDesignation="A.C.T."/>
            <Concept code="166" codeSystem="1.2.250.1.213.1.6.1.8" dateFin="" dateMaj="20050706000000" dateValid="19790101000000" displayName="Etablissement d'accueil mère-enfant" longDesignation="Etablissement d'Accueil Mère-Enfant" shortDesignation="Etab.Acc.Mère-Enfant"/>
            <Concept code="167" codeSystem="1.2.250.1.213.1.6.1.8" dateFin="20140331000000" dateMaj="20140331000000" dateValid="19790101000000" displayName="Crèche collective" longDesignation="Crèche Collective" shortDesignation="Crèche Collective"/>
            <Concept code="168" codeSystem="1.2.250.1.213.1.6.1.8" dateFin="20140331000000" dateMaj="20140331000000" dateValid="19790101000000" displayName="Service accueil familial pour la petite enfance" longDesignation="Service Accueil Familial pour la Petite Enfance" shortDesignation="Accueil Familial"/>
            <Concept code="169" codeSystem="1.2.250.1.213.1.6.1.8" dateFin="20140331000000" dateMaj="20140331000000" dateValid="19790101000000" displayName="Crèche multi-accueil collectif et familial" longDesignation="Crèche Multi Accueil Collectif et Familial" shortDesignation="Crèche Fam.et Coll."/>
            <Concept code="170" codeSystem="1.2.250.1.213.1.6.1.8" dateFin="20140331000000" dateMaj="20140331000000" dateValid="19790101000000" displayName="Halte-garderie" longDesignation="Halte Garderie" shortDesignation="Halte Garderie"/>
            <Concept code="171" codeSystem="1.2.250.1.213.1.6.1.8" dateFin="20140331000000" dateMaj="20140331000000" dateValid="19790101000000" displayName="Garderie, Jardin d'enfants" longDesignation="Garderie et Jardin d'Enfants" shortDesignation="Garderie Jardin Enf."/>
            <Concept code="172" codeSystem="1.2.250.1.213.1.6.1.8" dateFin="" dateMaj="20050706000000" dateValid="19790101000000" displayName="Pouponnière à caractère social" longDesignation="Pouponnière à Caractère Social" shortDesignation="Pouponnière Car.Soc."/>
            <Concept code="173" codeSystem="1.2.250.1.213.1.6.1.8" dateFin="20130625000000" dateMaj="19790123000000" dateValid="19790101000000" displayName="Pouponnière à caractère sanitaire" longDesignation="Pouponnière à Caractère Sanitaire" shortDesignation="Pouponnière Car.San."/>
            <Concept code="174" codeSystem="1.2.250.1.213.1.6.1.8" dateFin="20140331000000" dateMaj="20140331000000" dateValid="20000801000000" displayName="Etablissement d'accueil collectif régulier et occasionnel" longDesignation="Etablissement d'Accueil Collectif Régulier et Occasionnel" shortDesignation="Acc.Collect.Rég&amp;Occ."/>
            <Concept code="175" codeSystem="1.2.250.1.213.1.6.1.8" dateFin="" dateMaj="20050706000000" dateValid="19790101000000" displayName="Foyer de l'enfance" longDesignation="Foyer de l'Enfance" shortDesignation="Foyer de l'Enfance"/>
            <Concept code="176" codeSystem="1.2.250.1.213.1.6.1.8" dateFin="" dateMaj="20050706000000" dateValid="19790101000000" displayName="Village d'enfants" longDesignation="Village d'Enfants" shortDesignation="Village d'Enfants"/>
            <Concept code="177" codeSystem="1.2.250.1.213.1.6.1.8" dateFin="" dateMaj="20050706000000" dateValid="19790101000000" displayName="Maison d'enfants à caractère social" longDesignation="Maison d'Enfants à Caractère Social" shortDesignation="Mais.Enf.Car.Social"/>
            <Concept code="178" codeSystem="1.2.250.1.213.1.6.1.8" dateFin="" dateMaj="20060124000000" dateValid="19790101000000" displayName="Centre d'accueil et d'accompagnement à la réduction des risques pour usagers de drogues (CAARUD)" longDesignation="Ctre.Accueil- Accomp.Réduc.Risq.Usag. Drogues (C.A.A.R.U.D.)" shortDesignation="C.A.A.R.U.D."/>
            <Concept code="179" codeSystem="1.2.250.1.213.1.6.1.8" dateFin="20130625000000" dateMaj="19940705000000" dateValid="19790101000000" displayName="Maison d'enfants à caractère sanitaire permanente (MECS)" longDesignation="Maison d'Enfants à Caractère Sanitaire Permanente" shortDesignation="M.E.C.S. Permanente"/>
            <Concept code="180" codeSystem="1.2.250.1.213.1.6.1.8" dateFin="" dateMaj="20061019000000" dateValid="19790101000000" displayName="Lits halte soins santé (LHSS)" longDesignation="Lits Halte Soins Santé (L.H.S.S.)" shortDesignation="L.H.S.S."/>
            <Concept code="181" codeSystem="1.2.250.1.213.1.6.1.8" dateFin="20160106000000" dateMaj="20160106000000" dateValid="19790101000000" displayName="Maison familiale de vacances" longDesignation="Maison Familiale de Vacances" shortDesignation="Mais. Fam. Vacances"/>
            <Concept code="182" codeSystem="1.2.250.1.213.1.6.1.8" dateFin="" dateMaj="20050706000000" dateValid="19790101000000" displayName="Service d'éducation spéciale et de soins à domicile (SESSAD)" longDesignation="Service d'Éducation Spéciale et de Soins à Domicile" shortDesignation="S.E.S.S.A.D."/>
            <Concept code="183" codeSystem="1.2.250.1.213.1.6.1.8" dateFin="" dateMaj="20050706000000" dateValid="19790101000000" displayName="Institut médico-éducatif (IME)" longDesignation="Institut Médico-Educatif (I.M.E.)" shortDesignation="I.M.E."/>
            <Concept code="184" codeSystem="1.2.250.1.213.1.6.1.8" dateFin="20050706000000" dateMaj="20050701000000" dateValid="19790101000000" displayName="Institut médico-pédagogique (IMP)" longDesignation="Institut Médico-Pédagogique (I.M.P.)" shortDesignation="I.M.P."/>
            <Concept code="185" codeSystem="1.2.250.1.213.1.6.1.8" dateFin="20050706000000" dateMaj="20050701000000" dateValid="19790101000000" displayName="Institut médico-professionnel (IMPro)" longDesignation="Institut Médico-Professionnel (I.M.Pro.)" shortDesignation="I.M.Pro."/>
            <Concept code="186" codeSystem="1.2.250.1.213.1.6.1.8" dateFin="" dateMaj="20050706000000" dateValid="19790101000000" displayName="Institut thérapeutique éducatif et pédagogique (ITEP)" longDesignation="Institut Thérapeutique Éducatif et Pédagogique (I.T.E.P.)" shortDesignation="I.T.E.P."/>
            <Concept code="188" codeSystem="1.2.250.1.213.1.6.1.8" dateFin="" dateMaj="20050706000000" dateValid="19790101000000" displayName="Etablissement pour enfants ou adolescents polyhandicapés" longDesignation="Etablissement pour Enfants ou Adolescents Polyhandicapés" shortDesignation="Etab.Enf.ado.Poly."/>
            <Concept code="189" codeSystem="1.2.250.1.213.1.6.1.8" dateFin="" dateMaj="20050706000000" dateValid="19790101000000" displayName="Centre médico-psycho-pédagogique (CMPP)" longDesignation="Centre Médico-Psycho-Pédagogique (C.M.P.P.)" shortDesignation="C.M.P.P."/>
            <Concept code="190" codeSystem="1.2.250.1.213.1.6.1.8" dateFin="" dateMaj="20050706000000" dateValid="19790101000000" displayName="Centre action médico-sociale précoce (CAMSP)" longDesignation="Centre Action Médico-Sociale Précoce (C.A.M.S.P.)" shortDesignation="C.A.M.S.P."/>
            <Concept code="191" codeSystem="1.2.250.1.213.1.6.1.8" dateFin="20050706000000" dateMaj="20050701000000" dateValid="19790101000000" displayName="Etablissement pour déficients moteurs cérébraux" longDesignation="Etablissement pour Déficients Moteurs Cérébraux" shortDesignation="Etab.Déf.Mot.Céréb."/>
            <Concept code="192" codeSystem="1.2.250.1.213.1.6.1.8" dateFin="" dateMaj="20181026120000" dateValid="19790101000000" displayName="Institut d'éducation motrice" longDesignation="Institut d'éducation motrice" shortDesignation="I.E.M."/>
            <Concept code="193" codeSystem="1.2.250.1.213.1.6.1.8" dateFin="20050706000000" dateMaj="20050701000000" dateValid="19790101000000" displayName="Etablissement pour déficients moteurs et moteurs cérébraux" longDesignation="Etablissement pour Déficients Moteurs et Moteurs Cérébraux" shortDesignation="Etab.Déf.Mot.Déf.M.C"/>
            <Concept code="194" codeSystem="1.2.250.1.213.1.6.1.8" dateFin="" dateMaj="20050706000000" dateValid="19790101000000" displayName="Institut pour déficients visuels" longDesignation="Institut pour Déficients Visuels" shortDesignation="Inst.Déf.Visuels"/>
            <Concept code="195" codeSystem="1.2.250.1.213.1.6.1.8" dateFin="" dateMaj="20050706000000" dateValid="19790101000000" displayName="Institut pour déficients auditifs" longDesignation="Institut pour Déficients Auditifs" shortDesignation="Inst.Déf.Auditifs"/>
            <Concept code="196" codeSystem="1.2.250.1.213.1.6.1.8" dateFin="" dateMaj="20231215120000" dateValid="19790101000000" displayName="Institut d'éducation sensorielle sourd-aveugle" longDesignation="Institut d'Education Sensorielle Sourd-Aveugle" shortDesignation="Inst.Ed.Sen.Sour.Ave"/>
            <Concept code="197" codeSystem="1.2.250.1.213.1.6.1.8" dateFin="" dateMaj="20130123000000" dateValid="20130123000000" displayName="Centre de soins d'accompagnement et de prévention en addictologie (CSAPA)" longDesignation="Centre soins accompagnement prévention addictologie (CSAPA)" shortDesignation="C.S.A.P.A."/>
            <Concept code="198" codeSystem="1.2.250.1.213.1.6.1.8" dateFin="" dateMaj="20210528120000" dateValid="19790101000000" displayName="Établissement et Service de Préorientation" longDesignation="Établissement et Service de Préorientation" shortDesignation="Etab.Serv.Préorient."/>
            <Concept code="199" codeSystem="1.2.250.1.213.1.6.1.8" dateFin="20150105000000" dateMaj="20150105000000" dateValid="19790101000000" displayName="Hospice" longDesignation="Hospice" shortDesignation="Hospice"/>
            <Concept code="200" codeSystem="1.2.250.1.213.1.6.1.8" dateFin="20150101000000" dateMaj="20150601000000" dateValid="19790101000000" displayName="Maison de retraite" longDesignation="Maison de Retraite" shortDesignation="Maison de Retraite"/>
            <Concept code="202" codeSystem="1.2.250.1.213.1.6.1.8" dateFin="" dateMaj="20200228120000" dateValid="19790101000000" displayName="Résidences autonomie" longDesignation="Résidences autonomie" shortDesignation="Résidences autonomie"/>
            <Concept code="205" codeSystem="1.2.250.1.213.1.6.1.8" dateFin="20201030120000" dateMaj="20201030120000" dateValid="19790101000000" displayName="Foyer club restaurant" longDesignation="Foyer Club Restaurant" shortDesignation="Foyer Club Restaur."/>
            <Concept code="207" codeSystem="1.2.250.1.213.1.6.1.8" dateFin="" dateMaj="20050706000000" dateValid="19790101000000" displayName="Centre de jour pour personnes âgées" longDesignation="Centre de Jour pour Personnes Agées" shortDesignation="Ctre.de Jour P.A."/>
            <Concept code="208" codeSystem="1.2.250.1.213.1.6.1.8" dateFin="20180629120000" dateMaj="20180629120000" dateValid="19790101000000" displayName="Service d'aide-ménagère à domicile" longDesignation="Service d'Aide Ménagère à Domicile" shortDesignation="Serv.Aide Ménag.Dom."/>
            <Concept code="209" codeSystem="1.2.250.1.213.1.6.1.8" dateFin="" dateMaj="20231030120000" dateValid="19790101000000" displayName="Service autonomie aide et soins" longDesignation="Service autonomie aide et soins (SAAS)" shortDesignation="S.A.A.S."/>
            <Concept code="212" codeSystem="1.2.250.1.213.1.6.1.8" dateFin="20180629120000" dateMaj="20180629120000" dateValid="19790101000000" displayName="Alarme médico-sociale" longDesignation="Alarme Médico-Sociale" shortDesignation="Alarm.Médico-Sociale"/>
            <Concept code="213" codeSystem="1.2.250.1.213.1.6.1.8" dateFin="" dateMaj="20181214120000" dateValid="20181214120000" displayName="Lits d'accueil médicalisés (L.A.M.)" longDesignation="Lits d'Accueil Médicalisés (L.A.M.)" shortDesignation="L.A.M."/>
            <Concept code="214" codeSystem="1.2.250.1.213.1.6.1.8" dateFin="" dateMaj="20050706000000" dateValid="19790101000000" displayName="Centre d'hébergement et de réinsertion sociale (CHRS)" longDesignation="Centre Hébergement &amp; Réinsertion Sociale (C.H.R.S.)" shortDesignation="C.H.R.S."/>
            <Concept code="215" codeSystem="1.2.250.1.213.1.6.1.8" dateFin="20080626000000" dateMaj="20080610000000" dateValid="20080601000000" displayName="Maison relais" longDesignation="Maison Relai" shortDesignation="Maison Relai"/>
            <Concept code="216" codeSystem="1.2.250.1.213.1.6.1.8" dateFin="" dateMaj="20200626120000" dateValid="20200626120000" displayName="Résidence Hôtelière à Vocation Sociale (R.H.V.S)" longDesignation="Résidence Hôtelière à Vocation Sociale (R.H.V.S)" shortDesignation="R.H.V.S."/>
            <Concept code="217" codeSystem="1.2.250.1.213.1.6.1.8" dateFin="20010731000000" dateMaj="19790123000000" dateValid="19790101000000" displayName="Cité de transit" longDesignation="Cité de Transit" shortDesignation="Cité de Transit"/>
            <Concept code="218" codeSystem="1.2.250.1.213.1.6.1.8" dateFin="" dateMaj="20050706000000" dateValid="19790101000000" displayName="Aire station nomades" longDesignation="Aire Station Nomades" shortDesignation="Aire Station Nomades"/>
            <Concept code="219" codeSystem="1.2.250.1.213.1.6.1.8" dateFin="" dateMaj="20050706000000" dateValid="19790101000000" displayName="Autre centre d'accueil" longDesignation="Autre Centre d'Accueil" shortDesignation="Autre Ctre.Accueil"/>
            <Concept code="220" codeSystem="1.2.250.1.213.1.6.1.8" dateFin="" dateMaj="19900105000000" dateValid="19790101000000" displayName="Centre social" longDesignation="Centre Social" shortDesignation="Ctre.Social"/>
            <Concept code="221" codeSystem="1.2.250.1.213.1.6.1.8" dateFin="" dateMaj="20050706000000" dateValid="19790101000000" displayName="Bureau d'aide psychologique universitaire (BAPU)" longDesignation="Bureau d'Aide Psychologique Universitaire (B.A.P.U.)" shortDesignation="B.A.P.U."/>
            <Concept code="223" codeSystem="1.2.250.1.213.1.6.1.8" dateFin="" dateMaj="19920929000000" dateValid="19790101000000" displayName="Protection maternelle et infantile (PMI)" longDesignation="Protection Maternelle et Infantile (P.M.I.)" shortDesignation="P.M.I."/>
            <Concept code="224" codeSystem="1.2.250.1.213.1.6.1.8" dateFin="" dateMaj="19940705000000" dateValid="19790101000000" displayName="Etablissement de consultation pré et post-natale" longDesignation="Etablissement de Consultation Pré et Post-natale" shortDesignation="Etab.Cons.P.Post-Nat"/>
            <Concept code="225" codeSystem="1.2.250.1.213.1.6.1.8" dateFin="19940919000000" dateMaj="19910301000000" dateValid="19790101000000" displayName="Consultations de nourrissons" longDesignation="Consultations de Nourrissons" shortDesignation="Consult.Nourrissons"/>
            <Concept code="228" codeSystem="1.2.250.1.213.1.6.1.8" dateFin="" dateMaj="20240329120000" dateValid="19790101000000" displayName="Centre de santé sexuelle" longDesignation="Centre de Santé Sexuelle" shortDesignation="Ctre.Santé.Sexuelle"/>
            <Concept code="229" codeSystem="1.2.250.1.213.1.6.1.8" dateFin="19940919000000" dateMaj="19910301000000" dateValid="19790101000000" displayName="Consultation problèmes naissance" longDesignation="Consultation Problèmes naissance" shortDesignation="Consult. Prob.Naiss."/>
            <Concept code="230" codeSystem="1.2.250.1.213.1.6.1.8" dateFin="" dateMaj="19940705000000" dateValid="19790101000000" displayName="Etablissement consultation protection infantile" longDesignation="Etablissement Consultation Protection Infantile" shortDesignation="Etab.Consul.Pro.Inf."/>
            <Concept code="231" codeSystem="1.2.250.1.213.1.6.1.8" dateFin="" dateMaj="19790123000000" dateValid="19790101000000" displayName="Etablissement d'information, de consultation et de conseil familial" longDesignation="Etablissement Information Consultation Conseil Familial" shortDesignation="Etab.Inf.Consult.Fam"/>
            <Concept code="233" codeSystem="1.2.250.1.213.1.6.1.8" dateFin="20150304000000" dateMaj="20150315000000" dateValid="19790101000000" displayName="Lactarium" longDesignation="Lactarium" shortDesignation="Lactarium"/>
            <Concept code="236" codeSystem="1.2.250.1.213.1.6.1.8" dateFin="" dateMaj="20050706000000" dateValid="19790101000000" displayName="Centre de placement familial socio-éducatif (CPFSE)" longDesignation="Centre Placement Familial Socio-Educatif (C.P.F.S.E.)" shortDesignation="C.P.F.S.E."/>
            <Concept code="237" codeSystem="1.2.250.1.213.1.6.1.8" dateFin="20050706000000" dateMaj="20050701000000" dateValid="19790101000000" displayName="Centre de placement familial spécialisé" longDesignation="Centre de Placement Familial Spécialisé" shortDesignation="Ctre. Plac.Fam.Spé."/>
            <Concept code="238" codeSystem="1.2.250.1.213.1.6.1.8" dateFin="" dateMaj="20050706000000" dateValid="19790101000000" displayName="Centre d'accueil familial spécialisé" longDesignation="Centre d'Accueil Familial Spécialisé" shortDesignation="Ctre.Acc.Fam.Spécia."/>
            <Concept code="241" codeSystem="1.2.250.1.213.1.6.1.8" dateFin="" dateMaj="20241025120000" dateValid="19790101000000" displayName="Établissement de Placement" longDesignation="Établissement de Placement" shortDesignation="Établissement de Placement"/>
            <Concept code="242" codeSystem="1.2.250.1.213.1.6.1.8 " dateFin="" dateMaj="20241025120000" dateValid="20241025120000" displayName="Service d’Activité de Jour" longDesignation="Service d’Activité de Jour" shortDesignation="Service d’Activité de Jour"/>
            <Concept code="246" codeSystem="1.2.250.1.213.1.6.1.8" dateFin="" dateMaj="20050706000000" dateValid="19790101000000" displayName="Etablissement et service d'aide par le travail (ESAT)" longDesignation="Etablissement et Service d'Aide par le Travail (E.S.A.T.)" shortDesignation="E.S.A.T."/>
            <Concept code="247" codeSystem="1.2.250.1.213.1.6.1.8" dateFin="" dateMaj="20050706000000" dateValid="19790101000000" displayName="Entreprise adaptée" longDesignation="Entreprise adaptée" shortDesignation="Entreprise adaptée"/>
            <Concept code="249" codeSystem="1.2.250.1.213.1.6.1.8" dateFin="" dateMaj="20210528120000" dateValid="19790101000000" displayName="Établissement et Service de Réadaptation Professionnelle" longDesignation="Établissement et Service de Réadaptation Professionnelle" shortDesignation="Etab.Serv.Réadap.Pro"/>
            <Concept code="250" codeSystem="1.2.250.1.213.1.6.1.8" dateFin="19940919000000" dateMaj="19910301000000" dateValid="19790101000000" displayName="Centre de réentrainement au travail" longDesignation="Centre Réentrainement au travail" shortDesignation="Ctre.Réentr.Travail"/>
            <Concept code="251" codeSystem="1.2.250.1.213.1.6.1.8" dateFin="19940919000000" dateMaj="19910301000000" dateValid="19790101000000" displayName="Maison de vacances pour handicapés" longDesignation="Maison Vacances pour Handicapés" shortDesignation="Maison Vac.handicap."/>
            <Concept code="252" codeSystem="1.2.250.1.213.1.6.1.8" dateFin="20181026120000" dateMaj="20181026120000" dateValid="19790101000000" displayName="Foyer d'hébergement d'adultes handicapés" longDesignation="Foyer Hébergement Adultes Handicapés" shortDesignation="Foyer Héberg.A.H."/>
            <Concept code="253" codeSystem="1.2.250.1.213.1.6.1.8" dateFin="20181026120000" dateMaj="20181026120000" dateValid="20020101000000" displayName="Foyer d'accueil polyvalent pour adultes handicapés" longDesignation="Foyer d'Accueil Polyvalent pour Adultes Handicapés" shortDesignation="Foyer Poly.A.H."/>
            <Concept code="255" codeSystem="1.2.250.1.213.1.6.1.8" dateFin="" dateMaj="20050706000000" dateValid="19790101000000" displayName="Maison d'accueil spécialisée (MAS)" longDesignation="Maison d'Accueil Spécialisée (M.A.S.)" shortDesignation="M.A.S."/>
            <Concept code="256" codeSystem="1.2.250.1.213.1.6.1.8" dateFin="" dateMaj="20050706000000" dateValid="19790101000000" displayName="Foyer de travailleurs migrants non transformé en résidence sociale" longDesignation="Foyer Travailleurs Migrants non transformé en Résidence Soc." shortDesignation="Foyer Trav. Migrants"/>
            <Concept code="257" codeSystem="1.2.250.1.213.1.6.1.8" dateFin="" dateMaj="20170707100000" dateValid="19790101000000" displayName="Foyers de jeunes travailleurs" longDesignation="Foyers de jeunes travailleurs" shortDesignation="F.J.T."/>
            <Concept code="258" codeSystem="1.2.250.1.213.1.6.1.8" dateFin="" dateMaj="20090121000000" dateValid="20090121000000" displayName="Maison relais, Pension de famille" longDesignation="Maisons Relais - Pensions de Famille" shortDesignation="Maisons Relais-Pens."/>
            <Concept code="259" codeSystem="1.2.250.1.213.1.6.1.8" dateFin="" dateMaj="20170707100000" dateValid="20090121000000" displayName="Autres résidences sociales" longDesignation="Autres résidences sociales" shortDesignation="Autres résidences sociales"/>
            <Concept code="261" codeSystem="1.2.250.1.213.1.6.1.8" dateFin="19990915000000" dateMaj="19990915000000" dateValid="19790101000000" displayName="DDASS" longDesignation="D.D.A.S.S." shortDesignation="D.D.A.S.S."/>
            <Concept code="262" codeSystem="1.2.250.1.213.1.6.1.8" dateFin="20050609000000" dateMaj="20050609000000" dateValid="19790101000000" displayName="Etablissement régional d'enseignement adapté" longDesignation="Etablissement Régional d'Enseignement Adapté" shortDesignation="E.R.E.A."/>
            <Concept code="265" codeSystem="1.2.250.1.213.1.6.1.8" dateFin="20050609000000" dateMaj="20050609000000" dateValid="19790101000000" displayName="Section d'éducation spéciale, classe atelier" longDesignation="Section Education Spéciale Classe Atelier" shortDesignation="Sect.Educ. Spéc.Clas"/>
            <Concept code="266" codeSystem="1.2.250.1.213.1.6.1.8" dateFin="" dateMaj="19790123000000" dateValid="19790101000000" displayName="Dispensaire antivénérien" longDesignation="Dispensaire Antivénérien" shortDesignation="Disp.Antivénérien"/>
            <Concept code="267" codeSystem="1.2.250.1.213.1.6.1.8" dateFin="" dateMaj="19790123000000" dateValid="19790101000000" displayName="Dispensaire antihansénien" longDesignation="Dispensaire Antihansénien" shortDesignation="Disp.Antihansénien"/>
            <Concept code="268" codeSystem="1.2.250.1.213.1.6.1.8" dateFin="" dateMaj="19790123000000" dateValid="19790101000000" displayName="Centre médico-scolaire" longDesignation="Centre Médico-Scolaire" shortDesignation="Ctre.Médico-Scolaire"/>
            <Concept code="269" codeSystem="1.2.250.1.213.1.6.1.8" dateFin="" dateMaj="19790123000000" dateValid="19790101000000" displayName="Centre de médecine universitaire" longDesignation="Centre de Médecine Universitaire" shortDesignation="Ctre.Méd.Universit."/>
            <Concept code="270" codeSystem="1.2.250.1.213.1.6.1.8" dateFin="" dateMaj="19790123000000" dateValid="19790101000000" displayName="Centre de médecine sportive" longDesignation="Centre de Médecine Sportive" shortDesignation="Ctre.Méd.Sportive"/>
            <Concept code="271" codeSystem="1.2.250.1.213.1.6.1.8" dateFin="" dateMaj="20170707100000" dateValid="19790101000000" displayName="Maison d'accueil Hospitalière" longDesignation="Maison d'accueil Hospitalière" shortDesignation="Maison d'accueil Hospitalière"/>
            <Concept code="272" codeSystem="1.2.250.1.213.1.6.1.8" dateFin="20051114000000" dateMaj="20100526000000" dateValid="19010101000000" displayName="Ecole d'ambulanciers" longDesignation="Ecole d'ambulanciers" shortDesignation="Ecole d'ambulanciers"/>
            <Concept code="273" codeSystem="1.2.250.1.213.1.6.1.8" dateFin="20051114000000" dateMaj="20100526000000" dateValid="19010101000000" displayName="Institut de formation en soins infirmiers (IFSI)" longDesignation="Institut de formation en soins infirmiers (I.F.S.I.)" shortDesignation="I.F.S.I."/>
            <Concept code="274" codeSystem="1.2.250.1.213.1.6.1.8" dateFin="20051114000000" dateMaj="20100526000000" dateValid="19010101000000" displayName="Ecole de sages-femmes" longDesignation="Ecole de sages_femmes" shortDesignation="Ecole sages-femmes"/>
            <Concept code="275" codeSystem="1.2.250.1.213.1.6.1.8" dateFin="20051114000000" dateMaj="20100526000000" dateValid="19010101000000" displayName="Ecole de masseurs-kinésithérapeutes" longDesignation="Ecole de masseurs-kinésithérapeutes" shortDesignation="Ecole masseurs-kiné"/>
            <Concept code="276" codeSystem="1.2.250.1.213.1.6.1.8" dateFin="20051114000000" dateMaj="20100526000000" dateValid="19010101000000" displayName="Ecole de laborantins d'analyses médicales" longDesignation="Ecole de laborantins d'analyses médicales" shortDesignation="Ecole laborantins am"/>
            <Concept code="277" codeSystem="1.2.250.1.213.1.6.1.8" dateFin="20051114000000" dateMaj="20100526000000" dateValid="19010101000000" displayName="Ecole de puéricultrices" longDesignation="Ecole de péricultrices" shortDesignation="Ecole péricultrices"/>
            <Concept code="278" codeSystem="1.2.250.1.213.1.6.1.8" dateFin="20051114000000" dateMaj="20100526000000" dateValid="19010101000000" displayName="Etablissement de formation polyvalent" longDesignation="Etablissement de formation polyvalent" shortDesignation="Etab.frm.polyvalent"/>
            <Concept code="279" codeSystem="1.2.250.1.213.1.6.1.8" dateFin="20051114000000" dateMaj="20100526000000" dateValid="19010101000000" displayName="Ecole de service social" longDesignation="Ecole de service social" shortDesignation="Ecole service social"/>
            <Concept code="280" codeSystem="1.2.250.1.213.1.6.1.8" dateFin="20051114000000" dateMaj="20100526000000" dateValid="19010101000000" displayName="Ecole d'éducateurs spécialisés" longDesignation="Ecole d'éducateurs spécialisés" shortDesignation="Ecole éduc. spé."/>
            <Concept code="281" codeSystem="1.2.250.1.213.1.6.1.8" dateFin="20051114000000" dateMaj="20100526000000" dateValid="19010101000000" displayName="Centre de formation d'aides-soignants" longDesignation="Centre de formation d'aides soignants" shortDesignation="Ctre.frm.aides soig"/>
            <Concept code="282" codeSystem="1.2.250.1.213.1.6.1.8" dateFin="20051114000000" dateMaj="20100526000000" dateValid="19010101000000" displayName="Ecole de pédicures-podologues" longDesignation="Ecole de pédicures-podologues" shortDesignation="Ecole pédi.podo"/>
            <Concept code="283" codeSystem="1.2.250.1.213.1.6.1.8" dateFin="20051114000000" dateMaj="20100526000000" dateValid="19010101000000" displayName="Ecole de manipulateurs d'électroradiologie médicale" longDesignation="Ecole de manipulateurs d'électro-radiologie" shortDesignation="Ecole manip.é-rad"/>
            <Concept code="284" codeSystem="1.2.250.1.213.1.6.1.8" dateFin="20051114000000" dateMaj="20100526000000" dateValid="19010101000000" displayName="Ecole de travailleuses familiales" longDesignation="Ecole de travailleuses familiales" shortDesignation="Ecole trav.famil."/>
            <Concept code="285" codeSystem="1.2.250.1.213.1.6.1.8" dateFin="20160106000000" dateMaj="20160106000000" dateValid="19790101000000" displayName="Centre de loisirs sans hébergement" longDesignation="Centres de Loisirs sans Hébergement" shortDesignation="Ctre.Loisirs ss.Héb."/>
            <Concept code="286" codeSystem="1.2.250.1.213.1.6.1.8" dateFin="" dateMaj="20050706000000" dateValid="19790101000000" displayName="Club, Equipe de prévention" longDesignation="Club Equipe de Prévention" shortDesignation="Club Equipe de Prév."/>
            <Concept code="289" codeSystem="1.2.250.1.213.1.6.1.8" dateFin="20131219000000" dateMaj="20131219000000" dateValid="19790101000000" displayName="Centre de soins infirmiers" longDesignation="Centre de Soins Infirmiers" shortDesignation="Ctre.Soins Infirm."/>
            <Concept code="292" codeSystem="1.2.250.1.213.1.6.1.8" dateFin="" dateMaj="19940705000000" dateValid="19790101000000" displayName="Centre hospitalier spécialisé de lutte contre les maladies mentales" longDesignation="Centre Hospitalier Spécialisé lutte Maladies Mentales" shortDesignation="C.H.S. Mal.Mentales"/>
            <Concept code="294" codeSystem="1.2.250.1.213.1.6.1.8" dateFin="" dateMaj="19790123000000" dateValid="19790101000000" displayName="Centre de consultations cancer" longDesignation="Centre de Consultations Cancer" shortDesignation="Ctre.Consul.Cancer"/>
            <Concept code="295" codeSystem="1.2.250.1.213.1.6.1.8" dateFin="" dateMaj="20200626120000" dateValid="19790101000000" displayName="Service AEMO et AED" longDesignation="Service AEMO et AED" shortDesignation="Service AEMO et AED"/>
            <Concept code="297" codeSystem="1.2.250.1.213.1.6.1.8" dateFin="19920101000000" dateMaj="20030304000000" dateValid="19790101000000" displayName="Dispensaire polyvalent" longDesignation="Dispensaire Polyvalent" shortDesignation="Disp. Polyvalent"/>
            <Concept code="300" codeSystem="1.2.250.1.213.1.6.1.8" dateFin="" dateMaj="20050524000000" dateValid="20050101000000" displayName="Ecole formant aux professions sanitaires" longDesignation="Ecoles Formant aux Professions Sanitaires" shortDesignation="Ecoles sanitaires"/>
            <Concept code="303" codeSystem="1.2.250.1.213.1.6.1.8" dateFin="20051114000000" dateMaj="20100526000000" dateValid="19010101000000" displayName="Ecole de conseillers en économie sociale et familiale" longDesignation="Ecole de conseillers en économie sociale et familiale" shortDesignation="Ecole C.E.S.F."/>
            <Concept code="304" codeSystem="1.2.250.1.213.1.6.1.8" dateFin="20051114000000" dateMaj="20100526000000" dateValid="19010101000000" displayName="Ecole d'ergothérapeutes" longDesignation="Ecole d'ergothérapeutes" shortDesignation="Ecole ergothérap."/>
            <Concept code="305" codeSystem="1.2.250.1.213.1.6.1.8" dateFin="20051114000000" dateMaj="20100526000000" dateValid="19010101000000" displayName="Ecole de psychomotriciens" longDesignation="Ecole de psycho-motriciens" shortDesignation="Ecole psycho-motric."/>
            <Concept code="306" codeSystem="1.2.250.1.213.1.6.1.8" dateFin="20051114000000" dateMaj="20100526000000" dateValid="19010101000000" displayName="Ecole d'infirmiers anesthésistes" longDesignation="Ecole d'infirmiers anesthésistes" shortDesignation="Ecole inf.anesth."/>
            <Concept code="307" codeSystem="1.2.250.1.213.1.6.1.8" dateFin="20051114000000" dateMaj="20100526000000" dateValid="19010101000000" displayName="Ecole d'infirmiers de bloc opératoire" longDesignation="Ecole d'infirmiers de bloc opératoire" shortDesignation="Ecole inf. bloc op."/>
            <Concept code="308" codeSystem="1.2.250.1.213.1.6.1.8" dateFin="20051114000000" dateMaj="20100526000000" dateValid="19010101000000" displayName="Centre de formation professionnelle de secteur psychiatrique" longDesignation="Centre de formation professionnelle de secteur psychiatrique" shortDesignation="Ctre frm.pro.sec.psy"/>
            <Concept code="309" codeSystem="1.2.250.1.213.1.6.1.8" dateFin="20051114000000" dateMaj="20100526000000" dateValid="19010101000000" displayName="Ecole de cadres infirmiers" longDesignation="Ecole de cadres infirmiers" shortDesignation="Ecole cdr.inf."/>
            <Concept code="310" codeSystem="1.2.250.1.213.1.6.1.8" dateFin="20051114000000" dateMaj="20100526000000" dateValid="19010101000000" displayName="Ecole de cadres de secteur psychiatrique" longDesignation="Ecole de cadres de secteur psychiatrique" shortDesignation="Ecole cdr.sect.psy."/>
            <Concept code="311" codeSystem="1.2.250.1.213.1.6.1.8" dateFin="20051114000000" dateMaj="20100526000000" dateValid="19010101000000" displayName="Ecole de cadres de masseurs-kinésithérapeutes" longDesignation="Ecole de cadres de masseurs-kinésithérapeutes" shortDesignation="Ecole cdr.mass-kiné."/>
            <Concept code="312" codeSystem="1.2.250.1.213.1.6.1.8" dateFin="20051114000000" dateMaj="20100526000000" dateValid="19010101000000" displayName="Ecole de cadres de manipulateurs d'électroradiologie médicale" longDesignation="Ecole de cadres de manipulateurs d'électro-radiologie" shortDesignation="Ecole cdr.mani.é-rad"/>
            <Concept code="313" codeSystem="1.2.250.1.213.1.6.1.8" dateFin="20051114000000" dateMaj="20100526000000" dateValid="19010101000000" displayName="Ecole d'éducateurs de jeunes enfants" longDesignation="Ecole d'éducateurs de jeunes enfants" shortDesignation="Ecole éduc.j.enf"/>
            <Concept code="314" codeSystem="1.2.250.1.213.1.6.1.8" dateFin="20051114000000" dateMaj="20100526000000" dateValid="19010101000000" displayName="Ecole d'éducateurs techniques spécialisés" longDesignation="Ecole d'éducateurs techniques spécialisés" shortDesignation="Ecole éduc.tech.spé."/>
            <Concept code="315" codeSystem="1.2.250.1.213.1.6.1.8" dateFin="20051114000000" dateMaj="20100526000000" dateValid="19010101000000" displayName="Ecole de moniteurs-éducateurs" longDesignation="Ecole de moniteurs-éducateurs" shortDesignation="Ecole moniteurs-éduc"/>
            <Concept code="316" codeSystem="1.2.250.1.213.1.6.1.8" dateFin="20051114000000" dateMaj="20100526000000" dateValid="19010101000000" displayName="Ecole d'aides médico-psychologiques" longDesignation="Ecole d'aides médico-psychologiques" shortDesignation="Ecole aid.méd-psycho"/>
            <Concept code="317" codeSystem="1.2.250.1.213.1.6.1.8" dateFin="20051114000000" dateMaj="20100526000000" dateValid="19010101000000" displayName="Ecole d'animateurs socio-éducatifs" longDesignation="Ecole d'animateurs socio-éducatifs" shortDesignation="Ecole ani.socio-éduc"/>
            <Concept code="319" codeSystem="1.2.250.1.213.1.6.1.8" dateFin="20051114000000" dateMaj="20100526000000" dateValid="19010101000000" displayName="Institut régional de formation des travailleurs sociaux" longDesignation="Inst. régional de formation des travailleurs sociaux" shortDesignation="I.R.F.T.S."/>
            <Concept code="320" codeSystem="1.2.250.1.213.1.6.1.8" dateFin="19990915000000" dateMaj="19990915000000" dateValid="19790101000000" displayName="SAMU, Centre 15" longDesignation="S.A.M.U. et Centre 15" shortDesignation="S.A.M.U et Centre 15"/>
            <Concept code="321" codeSystem="1.2.250.1.213.1.6.1.8" dateFin="19990915000000" dateMaj="19990915000000" dateValid="19790101000000" displayName="Unité mobile hospitalière" longDesignation="Unité Mobile Hospitalière" shortDesignation="Unité Mobile Hosp."/>
            <Concept code="322" codeSystem="1.2.250.1.213.1.6.1.8" dateFin="19990915000000" dateMaj="19990915000000" dateValid="19790101000000" displayName="Centre régional informatique hospitalière" longDesignation="Centre Rég.Informatiq.Hospit." shortDesignation="Ctre.Rég.Infor.Hosp."/>
            <Concept code="324" codeSystem="1.2.250.1.213.1.6.1.8" dateFin="" dateMaj="20050706000000" dateValid="19790101000000" displayName="Logement foyer non spécialisé" longDesignation="Logement Foyer non Spécialisé" shortDesignation="Log.Foyer non Spéc."/>
            <Concept code="326" codeSystem="1.2.250.1.213.1.6.1.8" dateFin="20051114000000" dateMaj="20100526000000" dateValid="19010101000000" displayName="Ecole de cadres" longDesignation="Ecole de cadres" shortDesignation="Ecole de cadres"/>
            <Concept code="327" codeSystem="1.2.250.1.213.1.6.1.8" dateFin="20190426120000" dateMaj="20190426120000" dateValid="19790101000000" displayName="Service d'ambulances" longDesignation="Service d'Ambulances" shortDesignation="Serv.Ambulances"/>
            <Concept code="328" codeSystem="1.2.250.1.213.1.6.1.8" dateFin="19940919000000" dateMaj="19851031000000" dateValid="19790101000000" displayName="Centre de consultation et soins dentaire" longDesignation="Centre Consultation Soins Dentaire" shortDesignation="Ctre.Cons.Soins.Dent"/>
            <Concept code="329" codeSystem="1.2.250.1.213.1.6.1.8" dateFin="19940919000000" dateMaj="19870119000000" dateValid="19790101000000" displayName="Sectorisation psychiatrique" longDesignation="Sectorisation Psychiatrique" shortDesignation="Sectorisation Psy."/>
            <Concept code="330" codeSystem="1.2.250.1.213.1.6.1.8" dateFin="" dateMaj="20050524000000" dateValid="20050101000000" displayName="Ecole formant aux professions sociales" longDesignation="Ecoles Formant aux Professions Sociales" shortDesignation="Ecoles sociales"/>
            <Concept code="340" codeSystem="1.2.250.1.213.1.6.1.8" dateFin="" dateMaj="20101125000000" dateValid="20101112000000" displayName="Service mandataire judiciaire à la protection des majeurs" longDesignation="Service mandataire judiciaire à la protection des majeurs" shortDesignation="M.J.P.M."/>
            <Concept code="341" codeSystem="1.2.250.1.213.1.6.1.8" dateFin="" dateMaj="20101125000000" dateValid="20101112000000" displayName="Service dédié aux mesures d'accompagnement social personnalisé" longDesignation="Service dédié mesures d'accompagnement social personnalisé" shortDesignation="M.A.S.P."/>
            <Concept code="342" codeSystem="1.2.250.1.213.1.6.1.8" dateFin="" dateMaj="20101125000000" dateValid="20101112000000" displayName="Service d'information et de soutien aux tuteurs familiaux" longDesignation="Service d'information et de soutien aux tuteurs familiaux" shortDesignation="S.I.S.T.F."/>
            <Concept code="343" codeSystem="1.2.250.1.213.1.6.1.8" dateFin="20050609000000" dateMaj="20050609000000" dateValid="19790101000000" displayName="Equipe de préparation et de suite au reclassement (EPSR)" longDesignation="Equipe Préparation et Suite Reclassement (EPSR)" shortDesignation="E.P.S.R."/>
            <Concept code="344" codeSystem="1.2.250.1.213.1.6.1.8" dateFin="" dateMaj="20101125000000" dateValid="20101112000000" displayName="Service délégué aux prestations familiales" longDesignation="Service délégué aux prestations familiales" shortDesignation="D.P.F."/>
            <Concept code="345" codeSystem="1.2.250.1.213.1.6.1.8" dateFin="" dateMaj="19790123000000" dateValid="19790101000000" displayName="Service de tutelle aux prestations sociales adultes" longDesignation="Service Tutelle Prestation Sociale" shortDesignation="Serv.Tut.Prest.Soc."/>
            <Concept code="346" codeSystem="1.2.250.1.213.1.6.1.8" dateFin="20180629120000" dateMaj="20180629120000" dateValid="19790101000000" displayName="Service de travailleuses familiales" longDesignation="Service de Travailleuses Familiales" shortDesignation="Serv.Trav.Familiales"/>
            <Concept code="347" codeSystem="1.2.250.1.213.1.6.1.8" dateFin="" dateMaj="19880505000000" dateValid="19790101000000" displayName="Centre d'examens de santé" longDesignation="Centre d'Examens de Santé" shortDesignation="Ctre.Examens Santé"/>
            <Concept code="349" codeSystem="1.2.250.1.213.1.6.1.8" dateFin="20051114000000" dateMaj="20100526000000" dateValid="19010101000000" displayName="Ecole de cadres de sages-femmes" longDesignation="Ecole de cadres de sages-femmes" shortDesignation="Ecole cdr.sg-femmes"/>
            <Concept code="350" codeSystem="1.2.250.1.213.1.6.1.8" dateFin="20051114000000" dateMaj="20100526000000" dateValid="19010101000000" displayName="Centre de formation d'auxiliaires de puériculture" longDesignation="Centre de formation d'auxiliaires de puériculture" shortDesignation="Ctre frm.auxi.puéri"/>
            <Concept code="352" codeSystem="1.2.250.1.213.1.6.1.8" dateFin="19940919000000" dateMaj="19851031000000" dateValid="19790101000000" displayName="Centre de psychothérapie" longDesignation="Centre de Psychothérapie" shortDesignation="Ctre.Psychothérapie"/>
            <Concept code="353" codeSystem="1.2.250.1.213.1.6.1.8" dateFin="19940919000000" dateMaj="19910301000000" dateValid="19790101000000" displayName="Hôpital de jour spécialités médicales" longDesignation="Hôpital de Jour Spécialités Médicales" shortDesignation="Hop.Jour Spéc.Méd."/>
            <Concept code="354" codeSystem="1.2.250.1.213.1.6.1.8" dateFin="" dateMaj="20050706000000" dateValid="19790101000000" displayName="Service de soins infirmiers à domicile (SSIAD)" longDesignation="Service de Soins Infirmiers A Domicile (S.S.I.A.D)" shortDesignation="S.S.I.A.D."/>
            <Concept code="355" codeSystem="1.2.250.1.213.1.6.1.8" dateFin="" dateMaj="19790123000000" dateValid="19790101000000" displayName="Centre hospitalier (CH)" longDesignation="Centre Hospitalier (C.H.)" shortDesignation="C.H."/>
            <Concept code="357" codeSystem="1.2.250.1.213.1.6.1.8" dateFin="19990915000000" dateMaj="19990915000000" dateValid="19790101000000" displayName="Association d'aide aux insuffisants respiratoires" longDesignation="Association Aide aux Insuffisants Respiratoires" shortDesignation="Assoc.Aide Ins.Resp."/>
            <Concept code="359" codeSystem="1.2.250.1.213.1.6.1.8" dateFin="" dateMaj="19790123000000" dateValid="19790101000000" displayName="Centre circonscription sanitaire et sociale" longDesignation="Centre Circonscription Sanitaire et Sociale" shortDesignation="Ctre.Circons.San.Soc"/>
            <Concept code="361" codeSystem="1.2.250.1.213.1.6.1.8" dateFin="19990915000000" dateMaj="19990915000000" dateValid="19790101000000" displayName="Centre de cure médicale" longDesignation="Centre de Cure Médicale" shortDesignation="Ctre.Cure Médicale"/>
            <Concept code="362" codeSystem="1.2.250.1.213.1.6.1.8" dateFin="" dateMaj="19940705000000" dateValid="19790101000000" displayName="Etablissement de soins longue durée" longDesignation="Etablissement de Soins Longue Durée" shortDesignation="Etab.Soins Long.Dur."/>
            <Concept code="363" codeSystem="1.2.250.1.213.1.6.1.8" dateFin="19990915000000" dateMaj="19990915000000" dateValid="19790101000000" displayName="Centre de moyen et long séjour" longDesignation="Centre moyen et long séjour" shortDesignation="Ctre.moyen et long"/>
            <Concept code="365" codeSystem="1.2.250.1.213.1.6.1.8" dateFin="" dateMaj="19940705000000" dateValid="19790101000000" displayName="Etablissement de soins pluridisciplinaire" longDesignation="Etablissement de Soins Pluridisciplinaire" shortDesignation="Etab.Soins Pluridis."/>
            <Concept code="366" codeSystem="1.2.250.1.213.1.6.1.8" dateFin="" dateMaj="19800612000000" dateValid="19790101000000" displayName="Atelier thérapeutique" longDesignation="Atelier Thérapeutique" shortDesignation="Atelier Thérapeut."/>
            <Concept code="367" codeSystem="1.2.250.1.213.1.6.1.8" dateFin="20140331000000" dateMaj="20140331000000" dateValid="19790101000000" displayName="Maison d'enfants non conventionnée, ni habilitée" longDesignation="Maison d'Enfants non Conventionnée ni Habilitée" shortDesignation="Mais.Enfant n.C.n.H"/>
            <Concept code="368" codeSystem="1.2.250.1.213.1.6.1.8" dateFin="20180629120000" dateMaj="20180629120000" dateValid="19790101000000" displayName="Service de repas à domicile" longDesignation="Service de Repas à Domicile" shortDesignation="Serv.Repas Domicile"/>
            <Concept code="369" codeSystem="1.2.250.1.213.1.6.1.8" dateFin="20010731000000" dateMaj="19940705000000" dateValid="19790101000000" displayName="Centre d'adaptation à la vie active (CAVA)" longDesignation="Centre Adaptation Vie Active (C.A.V.A.)" shortDesignation="C.A.V.A."/>
            <Concept code="370" codeSystem="1.2.250.1.213.1.6.1.8" dateFin="" dateMaj="20181026120000" dateValid="20181026120000" displayName="Etablissement Expérimental pour personnes handicapées" longDesignation="Etablissement Expérimental pour personnes handicapées" shortDesignation="Etab.Expérim. pour PH"/>
            <Concept code="371" codeSystem="1.2.250.1.213.1.6.1.8" dateFin="20010731000000" dateMaj="19920929000000" dateValid="19790101000000" displayName="Service d'action socio-éducative pour familles en difficulté" longDesignation="Service Action Socio-Educative pour Familles en difficulté" shortDesignation="Serv.Act.Soc-Educ.F."/>
            <Concept code="373" codeSystem="1.2.250.1.213.1.6.1.8" dateFin="20051114000000" dateMaj="20100526000000" dateValid="19010101000000" displayName="Centre de formation supérieure des travailleurs sociaux" longDesignation="Centre de formation supérieure des travailleurs sociaux" shortDesignation="Ctre frm.sup.trv.scx"/>
            <Concept code="374" codeSystem="1.2.250.1.213.1.6.1.8" dateFin="" dateMaj="20050524000000" dateValid="19790101000000" displayName="Ecole nationale de santé publique (ENSP)" longDesignation="Ecole Nationale Santé Publique (E.N.S.P.)" shortDesignation="E.N.S.P."/>
            <Concept code="375" codeSystem="1.2.250.1.213.1.6.1.8" dateFin="19940919000000" dateMaj="19910301000000" dateValid="19790101000000" displayName="Classe d'adaptation" longDesignation="Classe d'Adaptation" shortDesignation="Classe d'Adaptation"/>
            <Concept code="376" codeSystem="1.2.250.1.213.1.6.1.8" dateFin="20050609000000" dateMaj="20050609000000" dateValid="19790101000000" displayName="Classe spéciale école primaire" longDesignation="Classe Spéciale Ecole Primaire" shortDesignation="Classe Spéc.Ecole.Pr"/>
            <Concept code="377" codeSystem="1.2.250.1.213.1.6.1.8" dateFin="20181026120000" dateMaj="20181026120000" dateValid="19790101000000" displayName="Etablissement expérimental pour enfance handicapée" longDesignation="Etablissement Expérimental pour Enfance Handicapée" shortDesignation="Etab.Expér.Enf.Hand."/>
            <Concept code="378" codeSystem="1.2.250.1.213.1.6.1.8" dateFin="" dateMaj="20050706000000" dateValid="19790101000000" displayName="Etablissement expérimental enfance protégée" longDesignation="Etablissement Expérimental Enfance Protégée" shortDesignation="Etab.Expér.Enf.Prot."/>
            <Concept code="379" codeSystem="1.2.250.1.213.1.6.1.8" dateFin="20181026120000" dateMaj="20181026120000" dateValid="19790101000000" displayName="Etablissement expérimental pour adultes handicapés" longDesignation="Etablissement Expérimental pour Adultes Handicapés" shortDesignation="Etab.Expér.A.H."/>
            <Concept code="380" codeSystem="1.2.250.1.213.1.6.1.8" dateFin="" dateMaj="20050706000000" dateValid="19790101000000" displayName="Etablissement expérimental autres adultes" longDesignation="Etablissement Expérimental Autres Adultes" shortDesignation="Etab.Expér.Autre.A."/>
            <Concept code="381" codeSystem="1.2.250.1.213.1.6.1.8" dateFin="" dateMaj="20050706000000" dateValid="19790101000000" displayName="Etablissement expérimental pour personnes âgées" longDesignation="Etablissement Expérimental pour Personnes Agées" shortDesignation="Etab.Expér.P.A."/>
            <Concept code="382" codeSystem="1.2.250.1.213.1.6.1.8" dateFin="20181026120000" dateMaj="20181026120000" dateValid="19790101000000" displayName="Foyer de vie pour adultes handicapés" longDesignation="Foyer de Vie pour Adultes Handicapés" shortDesignation="Foyer de vie A.H."/>
            <Concept code="386" codeSystem="1.2.250.1.213.1.6.1.8" dateFin="19940919000000" dateMaj="19910301000000" dateValid="19790101000000" displayName="Ecole secondaire spéciale" longDesignation="Ecole Secondaire Spéciale" shortDesignation="Ecole Secondaire Spé"/>
            <Concept code="390" codeSystem="1.2.250.1.213.1.6.1.8" dateFin="" dateMaj="20050706000000" dateValid="20020101000000" displayName="Etablissement d'accueil temporaire d'enfants handicapés" longDesignation="Etablissement d'Accueil Temporaire d'Enfants Handicapés" shortDesignation="Etab.Acc.Temp.E.H."/>
            <Concept code="393" codeSystem="1.2.250.1.213.1.6.1.8" dateFin="19940919000000" dateMaj="19910301000000" dateValid="19790101000000" displayName="Autre résidence à but lucratif pour personnes âgées" longDesignation="Autre résidence But lucratif pr personnes Âgées" shortDesignation="Aut.res.But luc.PA"/>
            <Concept code="394" codeSystem="1.2.250.1.213.1.6.1.8" dateFin="20150101000000" dateMaj="20150101000000" dateValid="19790101000000" displayName="Etablissement d'accueil temporaire pour personnes âgées" longDesignation="Etablissement d'Accueil Temporaire pour Personnes Agées" shortDesignation="Etab.Acc.Temp.P.A."/>
            <Concept code="395" codeSystem="1.2.250.1.213.1.6.1.8" dateFin="" dateMaj="20050706000000" dateValid="20020101000000" displayName="Etablissement d'accueil temporaire pour adultes handicapés" longDesignation="Etablissement d'Accueil Temporaire pour Adultes Handicapés" shortDesignation="Etab.Acc.Temp.A.H."/>
            <Concept code="396" codeSystem="1.2.250.1.213.1.6.1.8" dateFin="" dateMaj="20050706000000" dateValid="19790101000000" displayName="Foyer d'hébergement pour enfants et adolescents handicapés" longDesignation="Foyer Hébergement Enfants et Adolescents Handicapés" shortDesignation="Foyer Heb.Enf.Ado.H."/>
            <Concept code="397" codeSystem="1.2.250.1.213.1.6.1.8" dateFin="20050706000000" dateMaj="20050701000000" dateValid="19790101000000" displayName="Service auxiliaire de vie pour handicapés" longDesignation="Service Auxiliaire de Vie pour Handicapés" shortDesignation="Serv.Auxil.Vie Hand."/>
            <Concept code="398" codeSystem="1.2.250.1.213.1.6.1.8" dateFin="20140331000000" dateMaj="20140331000000" dateValid="19790101000000" displayName="Crèche parentale" longDesignation="Crèche Parentale" shortDesignation="Crèche Parentale"/>
            <Concept code="399" codeSystem="1.2.250.1.213.1.6.1.8" dateFin="20140331000000" dateMaj="20140331000000" dateValid="19790101000000" displayName="Halte garderie parentale" longDesignation="Halte Garderie Parentale" shortDesignation="Halte Garderie Par."/>
            <Concept code="400" codeSystem="1.2.250.1.213.1.6.1.8" dateFin="" dateMaj="19821119000000" dateValid="19790101000000" displayName="Centre de services pour associations" longDesignation="Centre de Services pour Associations" shortDesignation="Ctre.Services Assoc."/>
            <Concept code="401" codeSystem="1.2.250.1.213.1.6.1.8" dateFin="19990915000000" dateMaj="19990915000000" dateValid="19790101000000" displayName="DRASS" longDesignation="D.R.A.S.S." shortDesignation="D.R.A.S.S."/>
            <Concept code="402" codeSystem="1.2.250.1.213.1.6.1.8" dateFin="" dateMaj="20050706000000" dateValid="19790101000000" displayName="Jardin d'enfants spécialisé" longDesignation="Jardin d'Enfants Spécialisé" shortDesignation="Jardin Enfants Spéc."/>
            <Concept code="403" codeSystem="1.2.250.1.213.1.6.1.8" dateFin="" dateMaj="19940705000000" dateValid="19790101000000" displayName="Service social spécialisé ou polyvalent de catégorie" longDesignation="Service Social Spécialisé ou Polyvalent de Catégorie" shortDesignation="Serv.Soc.Spéc.Pol.Ca"/>
            <Concept code="404" codeSystem="1.2.250.1.213.1.6.1.8" dateFin="20140331000000" dateMaj="20140331000000" dateValid="20000801000000" displayName="Etablissement d'accueil collectif parental régulier et occasionnel" longDesignation="Etablissement Acc.Collect.Parental Régulier &amp; Occasionnel" shortDesignation="Etab.Acc.Parental"/>
            <Concept code="405" codeSystem="1.2.250.1.213.1.6.1.8" dateFin="" dateMaj="19821208000000" dateValid="19790101000000" displayName="Service social polyvalent de secteur" longDesignation="Service Social Polyvalent de Secteur" shortDesignation="Serv.Soc.Polyv.Sect."/>
            <Concept code="411" codeSystem="1.2.250.1.213.1.6.1.8" dateFin="" dateMaj="20050706000000" dateValid="19790101000000" displayName="Intermédiaire de placement social" longDesignation="Intermédiaire de Placement Social" shortDesignation="Interméd.Pla.Social"/>
            <Concept code="412" codeSystem="1.2.250.1.213.1.6.1.8" dateFin="" dateMaj="19831221000000" dateValid="19790101000000" displayName="Appartement thérapeutique" longDesignation="Appartement Thérapeutique" shortDesignation="Appart.Thérapeutique"/>
            <Concept code="413" codeSystem="1.2.250.1.213.1.6.1.8" dateFin="19990915000000" dateMaj="19990915000000" dateValid="19790101000000" displayName="Centres d'études et de conservation des oeufs et du sperme" longDesignation="C.E.C.O.S" shortDesignation="C.E.C.O.S"/>
            <Concept code="414" codeSystem="1.2.250.1.213.1.6.1.8" dateFin="19990915000000" dateMaj="19990915000000" dateValid="19790101000000" displayName="Centre antipoison" longDesignation="Centre Anti Poison" shortDesignation="Centre Anti Poison"/>
            <Concept code="415" codeSystem="1.2.250.1.213.1.6.1.8" dateFin="" dateMaj="19871230000000" dateValid="19790101000000" displayName="Service médico-psychologique régional (SMPR)" longDesignation="Service Médico-Psychologique Régional (S.M.P.R.)" shortDesignation="S.M.P.R."/>
            <Concept code="418" codeSystem="1.2.250.1.213.1.6.1.8" dateFin="20241025120000" dateMaj="20241025120000" dateValid="19790101000000" displayName="Service d'enquêtes sociales (SES)" longDesignation="Service d'Enquêtes Sociales (S.E.S.)" shortDesignation="Serv.Enq.Sociales"/>
            <Concept code="419" codeSystem="1.2.250.1.213.1.6.1.8" dateFin="19990915000000" dateMaj="19990915000000" dateValid="19790101000000" displayName="Centre d'accueil toxicomanes" longDesignation="Centre d'Accueil Toxicomanes" shortDesignation="Ctre.Acc.Toxico."/>
            <Concept code="420" codeSystem="1.2.250.1.213.1.6.1.8" dateFin="20010731000000" dateMaj="19940705000000" dateValid="19790101000000" displayName="Entreprise d'insertion" longDesignation="Entreprise d'Insertion" shortDesignation="Entreprise Insertion"/>
            <Concept code="421" codeSystem="1.2.250.1.213.1.6.1.8" dateFin="20051114000000" dateMaj="20100526000000" dateValid="19010101000000" displayName="Centre d'enseignement aux secours d'urgence" longDesignation="Centre d'enseignement aux secours d'urgence" shortDesignation="C.E.S.U."/>
            <Concept code="422" codeSystem="1.2.250.1.213.1.6.1.8" dateFin="" dateMaj="19860204000000" dateValid="19790101000000" displayName="Traitements spécialisés à domicile" longDesignation="Traitements Spécialisés à Domicile" shortDesignation="Trait.Spéc.Domicile"/>
            <Concept code="423" codeSystem="1.2.250.1.213.1.6.1.8" dateFin="20051114000000" dateMaj="20100526000000" dateValid="19010101000000" displayName="Ecole des cadres de laborantins d'analyses médicales" longDesignation="Ecole des cadres de laborantins d'analyses médicales" shortDesignation="Ecole cdr.labor.am"/>
            <Concept code="425" codeSystem="1.2.250.1.213.1.6.1.8" dateFin="" dateMaj="19870119000000" dateValid="19790101000000" displayName="Centre d'accueil thérapeutique à temps partiel (CATTP)" longDesignation="Centre d'Accueil Thérapeutique à temps partiel (C.A.T.T.P.)" shortDesignation="C.A.T.T.P."/>
            <Concept code="426" codeSystem="1.2.250.1.213.1.6.1.8" dateFin="" dateMaj="20130517000000" dateValid="19790101000000" displayName="Syndicat inter hospitalier (SIH)" longDesignation="Syndicat Inter Hospitalier (S.I.H.)" shortDesignation="S.I.H."/>
            <Concept code="427" codeSystem="1.2.250.1.213.1.6.1.8" dateFin="20241025120000" dateMaj="20241025120000" dateValid="19790101000000" displayName="Service éducatif auprès des tribunaux (SEAT)" longDesignation="Service Educatif Auprès des Tribunaux (S.E.A.T.)" shortDesignation="S.E.A.T."/>
            <Concept code="430" codeSystem="1.2.250.1.213.1.6.1.8" dateFin="" dateMaj="19910527000000" dateValid="19790101000000" displayName="Centre postcure pour malades mentaux" longDesignation="Centre Postcure Malades Mentaux" shortDesignation="Ctre.P-Cure Mal.Men."/>
            <Concept code="431" codeSystem="1.2.250.1.213.1.6.1.8" dateFin="20130625000000" dateMaj="19910527000000" dateValid="19790101000000" displayName="Centre postcure pour alcooliques" longDesignation="Centre Postcure pour Alcooliques" shortDesignation="Ctre.P-Cure Alcool."/>
            <Concept code="432" codeSystem="1.2.250.1.213.1.6.1.8" dateFin="19990915000000" dateMaj="19990915000000" dateValid="19790101000000" displayName="Centre postcure pour toxicomanes" longDesignation="Centre Postcure pour Toxicomanes" shortDesignation="Ctre.P-Cure Toxico."/>
            <Concept code="433" codeSystem="1.2.250.1.213.1.6.1.8" dateFin="" dateMaj="19910301000000" dateValid="19790101000000" displayName="Etablissement sanitaire des prisons" longDesignation="Etablissement Sanitaire des Prisons" shortDesignation="Etab.Sanit.Prisons"/>
            <Concept code="434" codeSystem="1.2.250.1.213.1.6.1.8" dateFin="20050609000000" dateMaj="20050609000000" dateValid="19790101000000" displayName="Classe spéciale en école maternelle" longDesignation="Classe Spéciale en Ecole Maternelle" shortDesignation="Classe Spéc.Ec.Mat."/>
            <Concept code="435" codeSystem="1.2.250.1.213.1.6.1.8" dateFin="20051114000000" dateMaj="20100526000000" dateValid="19010101000000" displayName="Centre de formation d'aide à domicile" longDesignation="Centre de formation d'aide à domicile" shortDesignation="Ctre frm.aide dom."/>
            <Concept code="436" codeSystem="1.2.250.1.213.1.6.1.8" dateFin="" dateMaj="20050524000000" dateValid="19790101000000" displayName="Ecoles formant aux professions sanitaires et sociales" longDesignation="Ecoles Formant aux Professions Sanitaires et Sociales" shortDesignation="Ecoles Pluriprof."/>
            <Concept code="437" codeSystem="1.2.250.1.213.1.6.1.8" dateFin="20181026120000" dateMaj="20181026120000" dateValid="19790101000000" displayName="Foyer d'accueil médicalisé pour adultes handicapés (FAM)" longDesignation="Foyer d'Accueil Médicalisé pour Adultes Handicapés (F.A.M.)" shortDesignation="F.A.M."/>
            <Concept code="438" codeSystem="1.2.250.1.213.1.6.1.8" dateFin="" dateMaj="19920929000000" dateValid="19790101000000" displayName="Centre de médecine collective" longDesignation="Centre de Médecine collective" shortDesignation="Ctre.Méd.Collect."/>
            <Concept code="439" codeSystem="1.2.250.1.213.1.6.1.8" dateFin="20131219000000" dateMaj="20131219000000" dateValid="19790101000000" displayName="Centre de santé polyvalent" longDesignation="Centre Santé Polyvalent" shortDesignation="Ctre.Santé Polyv."/>
            <Concept code="440" codeSystem="1.2.250.1.213.1.6.1.8" dateFin="" dateMaj="20241025120000" dateValid="19790101000000" displayName="Service d’Investigation Educative" longDesignation="Service d’Investigation Educative" shortDesignation="Service d’Investigation Educative"/>
            <Concept code="441" codeSystem="1.2.250.1.213.1.6.1.8" dateFin="" dateMaj="20241025120000" dateValid="19790101000000" displayName="Service d’Intervention Educative en Milieu Ouvert" longDesignation="Service d’Intervention Educative en Milieu Ouvert" shortDesignation="Service IEMO"/>
            <Concept code="442" codeSystem="1.2.250.1.213.1.6.1.8" dateFin="" dateMaj="20050706000000" dateValid="19790101000000" displayName="Centre provisoire d'hébergement" longDesignation="Centre Provisoire Hébergement (C.P.H.)" shortDesignation="C.P.H."/>
            <Concept code="443" codeSystem="1.2.250.1.213.1.6.1.8" dateFin="" dateMaj="20050706000000" dateValid="19790101000000" displayName="Centre d'accueil de demandeurs d'asile (CADA)" longDesignation="Centre Accueil Demandeurs Asile (C.A.D.A.)" shortDesignation="C.A.D.A."/>
            <Concept code="444" codeSystem="1.2.250.1.213.1.6.1.8" dateFin="" dateMaj="19940705000000" dateValid="19790101000000" displayName="Centre de crise et d'accueil permanent" longDesignation="Centre Crise Accueil Permanent" shortDesignation="Ctre.Crise Acc.Perm."/>
            <Concept code="445" codeSystem="1.2.250.1.213.1.6.1.8" dateFin="" dateMaj="20120504000000" dateValid="20150504000000" displayName="Service d'accompagnement médico-social pour adultes handicapés" longDesignation="Service d'accompagnement médico-social adultes handicapés" shortDesignation="S.A.M.S.A.H."/>
            <Concept code="446" codeSystem="1.2.250.1.213.1.6.1.8" dateFin="" dateMaj="20050706000000" dateValid="19790101000000" displayName="Service d'accompagnement à la vie sociale (SAVS)" longDesignation="Service d'Accompagnement à la Vie Sociale (S.A.V.S.)" shortDesignation="S.A.V.S."/>
            <Concept code="447" codeSystem="1.2.250.1.213.1.6.1.8" dateFin="20010731000000" dateMaj="19940705000000" dateValid="19790101000000" displayName="Entreprise intérim insertion" longDesignation="Entreprise Intérim Insertion" shortDesignation="Entrep.Intér.Insert."/>
            <Concept code="448" codeSystem="1.2.250.1.213.1.6.1.8" dateFin="" dateMaj="20181026120000" dateValid="20181026120000" displayName="Etablissement d'Accueil Médicalisé en tout ou partie personnes handicapées" longDesignation="Etab.Acc.Médicalisé en tout ou partie personnes handicapées" shortDesignation="E.A.M"/>
            <Concept code="449" codeSystem="1.2.250.1.213.1.6.1.8" dateFin="" dateMaj="20181026120000" dateValid="20181026120000" displayName="Etablissement d'Accueil Non Médicalisé pour personnes handicapées" longDesignation="Etab.Accueil Non Médicalisé pour personnes handicapées" shortDesignation="E.A.N.M"/>
            <Concept code="450" codeSystem="1.2.250.1.213.1.6.1.8" dateFin="20180629120000" dateMaj="20180629120000" dateValid="19790101000000" displayName="Service d'aide aux personnes âgées" longDesignation="Service d'Aide aux Personnes Agées" shortDesignation="Serv.Aide Pers.Agées"/>
            <Concept code="451" codeSystem="1.2.250.1.213.1.6.1.8" dateFin="20180629120000" dateMaj="20180629120000" dateValid="19790101000000" displayName="Service d'aide aux familles en difficulté" longDesignation="Service d'Aide aux Familles en Difficulté" shortDesignation="Serv.Aide Fam.Diff."/>
            <Concept code="452" codeSystem="1.2.250.1.213.1.6.1.8" dateFin="20010731000000" dateMaj="19940705000000" dateValid="19790101000000" displayName="Régie de quartier" longDesignation="Régie de Quartier" shortDesignation="Régie de Quartier"/>
            <Concept code="453" codeSystem="1.2.250.1.213.1.6.1.8" dateFin="20241025120000" dateMaj="20241025120000" dateValid="19970128000000" displayName="Service de réparation pénale" longDesignation="Service de Réparation Pénale" shortDesignation="Serv.Répar.Pénale"/>
            <Concept code="460" codeSystem="1.2.250.1.213.1.6.1.8" dateFin="" dateMaj="20231030120000" dateValid="20020101000000" displayName="Service autonomie aide" longDesignation="Service autonomie aide (SAA)" shortDesignation="S.A.A."/>
            <Concept code="461" codeSystem="1.2.250.1.213.1.6.1.8" dateFin="" dateMaj="20050706000000" dateValid="20020101000000" displayName="Centres de ressources SAI (sans aucune indication)" longDesignation="Centres de Ressources S.A.I. (Sans Aucune Indication)" shortDesignation="Ctre.Ressources"/>
            <Concept code="462" codeSystem="1.2.250.1.213.1.6.1.8" dateFin="" dateMaj="20241025120000" dateValid="20020101000000" displayName="Lieux de Vie et d’Accueil" longDesignation="Lieux de Vie et d’Accueil" shortDesignation="Lieux de Vie et d’Accueil"/>
            <Concept code="463" codeSystem="1.2.250.1.213.1.6.1.8" dateFin="" dateMaj="20050706000000" dateValid="20020101000000" displayName="Centre local d'information et de coordination de personnes âgées" longDesignation="Centres Locaux Information Coordination P.A.(C.L.I.C.)" shortDesignation="C.L.I.C."/>
            <Concept code="464" codeSystem="1.2.250.1.213.1.6.1.8" dateFin="" dateMaj="20231215120000" dateValid="20121105000000" displayName="Unité d'évaluation, de réentraînement et d'orientation sociale et-ou professionnelle" longDesignation="Unités Evaluation Réentraînement et d'Orient. Soc. et Pro." shortDesignation="U.E.R.O.S"/>
            <Concept code="500" codeSystem="1.2.250.1.213.1.6.1.8" dateFin="" dateMaj="20150106000000" dateValid="20150101000000" displayName="Etablissement d'hébergement pour personnes âgées dépendantes" longDesignation="Etablissement d'hébergement pour personnes âgées dépendantes" shortDesignation="EHPAD"/>
            <Concept code="501" codeSystem="1.2.250.1.213.1.6.1.8" dateFin="" dateMaj="20150106000000" dateValid="20150101000000" displayName="EHPA percevant des crédits d'assurance maladie" longDesignation="EHPA percevant des crédits d'assurance maladie" shortDesignation="EHPA perc crédit AM"/>
            <Concept code="502" codeSystem="1.2.250.1.213.1.6.1.8" dateFin="" dateMaj="20150106000000" dateValid="20150101000000" displayName="EHPA ne percevant pas des crédits d'assurance maladie" longDesignation="EHPA ne percevant pas des crédits d'assurance maladie" shortDesignation="EHPA sans crédit AM"/>
            <Concept code="601" codeSystem="1.2.250.1.213.1.6.1.8" dateFin="19990915000000" dateMaj="19990915000000" dateValid="19790101000000" displayName="Cabinet libéral médical" longDesignation="Cabinet Libéral Médical" shortDesignation="Cabinet Libé.Médical"/>
            <Concept code="602" codeSystem="1.2.250.1.213.1.6.1.8" dateFin="19990915000000" dateMaj="19990915000000" dateValid="19790101000000" displayName="Cabinet de groupe" longDesignation="Cabinet de Groupe" shortDesignation="Cabinet de Groupe"/>
            <Concept code="603" codeSystem="1.2.250.1.213.1.6.1.8" dateFin="" dateMaj="20120403000000" dateValid="20120328000000" displayName="Maison de santé (L6223-3)" longDesignation="Maison de santé (L.6223-3)" shortDesignation="Maison de santé"/>
            <Concept code="604" codeSystem="1.2.250.1.213.1.6.1.8" dateFin="" dateMaj="20200529120000" dateValid="20200529120000" displayName="Communauté Professionnelle Territoriale de Santé (CPTS)" longDesignation="Communauté Professionnelle Territoriale de Santé (CPTS)" shortDesignation="C.P.T.S." descriptionMetier="Les Communautés Professionnelles Territoriales de Santé (CPTS) ont été créées par la loi de modernisation de notre système de santé du 26 janvier 2016 (cf. articles Article L1434-12 et Article L1434-13 du code de la Santé Publique). Leur enregistrement est régi par l'instruction DGOS/DIR/DREES/DMSI/2020/12. Les CPTS sont un espace d'organisation et de coordination entre professionnels de santé et non pas des structures de soins : elles regroupent les professionnels de santé d'un même territoire qui souhaitent s'organiser - à leur initiative - autour d'un projet de santé pour répondre aux besoins de santé de la population. Les CPTS sont constituées entre des professionnels de santé, le cas échéant de maisons de santé, de centres de santé, de réseaux de santé, d'établissements de santé, d'établissements et de services médico-sociaux, des groupements de coopération sanitaire, et des groupements de coopération sociale et médicosociale. Grâce à l'accord conventionnel interprofessionnel (ACI) intervenu en 2019, les CPTS dont le projet de santé est validé par l'ARS sont enregistrés dans FINESS et peuvent bénéficier de financement de l'assurance maladie  Ne sont enregistrés dans FINESS que l'Entité Juridique et le siège social. Les établissements et professionnels constitutif d'une CPTS ne sont pas enregistrés dans FINESS."/>
            <Concept code="605" codeSystem="1.2.250.1.213.1.6.1.8" dateFin="19990915000000" dateMaj="19990915000000" dateValid="19790101000000" displayName="Cabinet d'auxiliaires médicaux" longDesignation="Cabinet d'Auxiliaires Médicaux" shortDesignation="Cabinet Aux.Médicaux"/>
            <Concept code="606" codeSystem="1.2.250.1.213.1.6.1.8" dateFin="" dateMaj="20220128120000" dateValid="20220128120000" displayName="Dispositif d'appui à la coordination (DAC)" longDesignation="Dispositif d'appui à la coordination (DAC)" shortDesignation="D.A.C"/>
            <Concept code="607" codeSystem="1.2.250.1.213.1.6.1.8" dateFin="" dateMaj="20220225120000" dateValid="20220225120000" displayName="Groupement Régional d'Appui au Développement de la e-Santé (GRADeS)" longDesignation="Groupement Régional d'Appui au Développement de la e-Santé (GRADeS)" shortDesignation="G.R.A.D.e.S"/>
            <Concept code="608" codeSystem="1.2.250.1.213.1.6.1.8" dateFin="" dateMaj="20220325120000" dateValid="20220325120000" displayName="Equipe mobile médico-sociale précarité (EMMSP)" longDesignation="Equipe mobile médico-sociale précarité (EMMSP)" shortDesignation="E.M.M.S.P"/>
            <Concept code="609" codeSystem="1.2.250.1.213.1.6.1.8" dateFin="" dateMaj="20221028120000" dateValid="20221028120000" displayName="Maison Départementale pour Personnes Handicapées (MDPH)" longDesignation="Maison Départementale pour Personnes Handicapées (MDPH)" shortDesignation="M.D.P.H"/>
            <Concept code="610" codeSystem="1.2.250.1.213.1.6.1.8" dateFin="" dateMaj="19830811000000" dateValid="19790101000000" displayName="Laboratoire d'analyses" longDesignation="Laboratoire d'Analyses" shortDesignation="Laboratoire Analyses"/>
            <Concept code="611" codeSystem="1.2.250.1.213.1.6.1.8" dateFin="" dateMaj="20100818000000" dateValid="20100723000000" displayName="Laboratoire de biologie médicale (LBM)" longDesignation="Laboratoire de Biologie Médicale" shortDesignation="Labo Biolog Médicale"/>
            <Concept code="612" codeSystem="1.2.250.1.213.1.6.1.8" dateFin="" dateMaj="20160113000000" dateValid="20160101000000" displayName="Autre laboratoire de biologie médicale sans FSE" longDesignation="Autre Laboratoire de Biologie Médicale sans FSE" shortDesignation="Autre Labo sans FSE"/>
            <Concept code="614" codeSystem="1.2.250.1.213.1.6.1.8" dateFin="" dateMaj="20230127120000" dateValid="20230127120000" displayName="Dispositif Spécifique Régional du Cancer (DSRC)" longDesignation="Dispositif Spécifique Régional du Cancer (DSRC)" shortDesignation="D.S.R.C."/>
            <Concept code="616" codeSystem="1.2.250.1.213.1.6.1.8" dateFin="" dateMaj="20230526120000" dateValid="20230526120000" displayName="Services de Prévention et de Santé au Travail (SPST)" longDesignation="Services de Prévention et de Santé au Travail (SPST)" shortDesignation="S.P.S.T."/>
            <Concept code="617" codeSystem="1.2.250.1.213.1.6.1.8" dateFin="" dateMaj="20230630120000" dateValid="20230630120000" displayName="Maison médicale de garde (MMG)" longDesignation="Maison médicale de garde (MMG)" shortDesignation="MMG"/>
            <Concept code="618" codeSystem="1.2.250.1.213.1.6.1.8" dateFin="" dateMaj="20240329120000" dateValid="20230630120000" displayName="Autre structure de soins non programmés (SNP)" longDesignation="Autre structure de soins non programmés (SNP)" shortDesignation="Autre structure de SNP"/>
            <Concept code="620" codeSystem="1.2.250.1.213.1.6.1.8" dateFin="" dateMaj="19810603000000" dateValid="19790101000000" displayName="Pharmacie d'officine" longDesignation="Pharmacie d'Officine" shortDesignation="Pharmacie d'Officine"/>
            <Concept code="621" codeSystem="1.2.250.1.213.1.6.1.8" dateFin="19990915000000" dateMaj="19990915000000" dateValid="19790101000000" displayName="Lunetterie médicale" longDesignation="Lunetterie Médicale" shortDesignation="Lunetterie Médicale"/>
            <Concept code="622" codeSystem="1.2.250.1.213.1.6.1.8" dateFin="19990915000000" dateMaj="19990915000000" dateValid="19790101000000" displayName="Centre d'appareillage et prothèse" longDesignation="Centre d'Appareillage &amp; Prothèse" shortDesignation="Ctre.Appar.&amp;Prothèse"/>
            <Concept code="623" codeSystem="1.2.250.1.213.1.6.1.8" dateFin="19990915000000" dateMaj="19990915000000" dateValid="19790101000000" displayName="Herboristerie" longDesignation="Herboristerie" shortDesignation="Herboristerie"/>
            <Concept code="624" codeSystem="1.2.250.1.213.1.6.1.8" dateFin="" dateMaj="20140117000000" dateValid="20140117000000" displayName="Laboratoire pharmaceutique préparant et délivrant des allergènes" longDesignation="Laboratoire pharmaceutique préparant délivrant allergènes" shortDesignation="Lab pharm allergènes"/>
            <Concept code="627" codeSystem="1.2.250.1.213.1.6.1.8" dateFin="" dateMaj="19960923000000" dateValid="19960923000000" displayName="Propharmacie" longDesignation="Propharmacie" shortDesignation="Propharmacie"/>
            <Concept code="628" codeSystem="1.2.250.1.213.1.6.1.8" dateFin="" dateMaj="19960923000000" dateValid="19960923000000" displayName="Pharmacie minière" longDesignation="Pharmacie Minière" shortDesignation="Pharmacie Minière"/>
            <Concept code="629" codeSystem="1.2.250.1.213.1.6.1.8" dateFin="" dateMaj="19960923000000" dateValid="19960923000000" displayName="Pharmacie mutualiste" longDesignation="Pharmacie Mutualiste" shortDesignation="Pharmacie Mutualiste"/>
            <Concept code="630" codeSystem="1.2.250.1.213.1.6.1.8" dateFin="" dateMaj="20150605000000" dateValid="20150605000000" displayName="Installation autonome de chirurgie esthétique" longDesignation="Installation autonome de chirurgie esthétique" shortDesignation="I.A.C.E."/>
            <Concept code="631" codeSystem="1.2.250.1.213.1.6.1.8" dateFin="" dateMaj="20170707100000" dateValid="20170707100000" displayName="Maisons de naissance" longDesignation="Maisons de naissance" shortDesignation="Maisons de naissance"/>
            <Concept code="632" codeSystem="1.2.250.1.213.1.6.1.8" dateFin="" dateMaj="20170707100000" dateValid="20170707100000" displayName="Structure Dispensatrice à domicile d'Oxygène à usage médical" longDesignation="Structure Dispensatrice à domicile d'Oxygène à usage médical" shortDesignation="Struc. Disp. Oxygène Médical"/>
            <Concept code="633" codeSystem="1.2.250.1.213.1.6.1.8" dateFin="" dateMaj="20200828120000" dateValid="20200828120000" displayName="Structure Expérimentale en Santé" longDesignation="Structure Expérimentale en Santé" shortDesignation="Struct.Expér.Santé"/>
            <Concept code="636" codeSystem="1.2.250.1.213.1.6.1.8" dateFin="" dateMaj="20181214120000" dateValid="20181214120000" displayName="Centre de soins et de prévention" longDesignation="Centre de soins et de prévention" shortDesignation="Centre soins prév."/>
            <Concept code="637" codeSystem="1.2.250.1.213.1.6.1.8" dateFin="" dateMaj="20230922120000" dateValid="20230922120000" displayName="Centre de Lutte Antituberculeuse" longDesignation="Centre de Lutte Antituberculeuse (CLAT)" shortDesignation="C.L.A.T."/>
            <Concept code="638" codeSystem="1.2.250.1.213.1.6.1.8" dateFin="" dateMaj="20230922120000" dateValid="20230922120000" displayName="Centre gratuit d'information de dépistage et de diagnostic" longDesignation="Centre gratuit d'information de dépistage et de diagnostic (CeGIDD)" shortDesignation="C.e.G.I.D.D."/>
            <Concept code="639" codeSystem="1.2.250.1.213.1.6.1.8" dateFin="" dateMaj="20230922120000" dateValid="20230922120000" displayName="Sociétés de téléconsultation" longDesignation="Sociétés de téléconsultation (STLC)" shortDesignation="S.T.L.C."/>
            <Concept code="640" codeSystem="1.2.250.1.213.1.6.1.8" dateFin="" dateMaj="20231030120000" dateValid="20231030120000" displayName="Service d'aide et d'accompagnement à domicile aux familles" longDesignation="Service d'aide et d'accompagnement à domicile aux familles (SAADF)" shortDesignation="S.A.A.D.F."/>
            <Concept code="641" codeSystem="1.2.250.1.213.1.6.1.8" dateFin="" dateMaj="20240223120000" dateValid="20240223120000" displayName="Antenne de Pharmacie d'officine" longDesignation="Antenne de Pharmacie d'officine" shortDesignation="Antenne Pharmacie Officine"/>
            <Concept code="642" codeSystem="1.2.250.1.213.1.6.1.8" dateFin="" dateMaj="20240628120000" dateValid="20240628120000" displayName="Services départementaux d'incendie et de secours" longDesignation="Services départementaux d'incendie et de secours" shortDesignation="S.D.I.S."/>
            <Concept code="643" codeSystem="1.2.250.1.213.1.6.1.8" dateFin="" dateMaj="20240531120000" dateValid="20240531120000" displayName="Service d'évaluation de la minorité et de l'isolement pour les personnes se déclarant mineures (SEMIPM)" longDesignation="Serv. d'éval de la minorité de l'isolement pour les pers. se déclarant mineures" shortDesignation="S.E.M.I.P.M."/>
            <Concept code="644" codeSystem="1.2.250.1.213.1.6.1.8" dateFin="" dateMaj="20240531120000" dateValid="20240531120000" displayName="Etablissement de mise à l'abri pour les personnes se déclarant mineures non accompagnées (EMAMNA)" longDesignation="Etab. de mise à l'abri pour les pers. se déclarant mineures non accompagnées" shortDesignation="E.M.A.M.N.A."/>
            <Concept code="645" codeSystem="1.2.250.1.213.1.6.1.8" dateFin="" dateMaj="20240927120000" dateValid="20240927120000" displayName="Centre de Vaccination" longDesignation="Centre de Vaccination" shortDesignation="C.V."/>
            <Concept code="646" codeSystem="1.2.250.1.213.1.6.1.8" dateFin="" dateMaj="20241025120000" dateValid="20240927120000" displayName="Centre de Vaccination Internationale" longDesignation="Centre de Vaccination Internationale" shortDesignation="C.V.I."/>
            <Concept code="647" codeSystem="1.2.250.1.213.1.6.1.8 " dateFin="" dateMaj="20250228120000" dateValid="20240927120000" displayName="Equipe de Soins Spécialisés" longDesignation="Equipe de Soins Spécialisés" shortDesignation="E.S.S."/>
            <Concept code="648" codeSystem="1.2.250.1.213.1.6.1.8" dateFin="" dateMaj="20241025120000" dateValid="20241025120000" displayName="Structure qui contribue au Service d'Accès aux Soins" longDesignation="Structure qui contribue au Service d'Accès aux Soins" shortDesignation="Structure qui contribue au SAS"/>
            <Concept code="690" codeSystem="1.2.250.1.213.1.6.1.8" dateFin="20240223120000" dateMaj="20240223120000" dateValid="19960923000000" displayName="Etablissement de fabrication annexe à une officine" longDesignation="Etablissement de Fabrication Annexe à une Officine" shortDesignation="Fab.Annexe Officine"/>
            <Concept code="695" codeSystem="1.2.250.1.213.1.6.1.8" dateFin="" dateMaj="20190529120000" dateValid="20190529120000" displayName="Groupement de coopération sanitaire de moyens - Exploitant" longDesignation="Groupement de coopération sanitaire de moyens - Exploitant" shortDesignation="GCS Exploitant"/>
            <Concept code="696" codeSystem="1.2.250.1.213.1.6.1.8" dateFin="" dateMaj="20110504000000" dateValid="20110504000000" displayName="Groupement de coopération sanitaire de moyens" longDesignation="Groupement de coopération sanitaire de moyens" shortDesignation="GCS-Moyens"/>
            <Concept code="697" codeSystem="1.2.250.1.213.1.6.1.8" dateFin="" dateMaj="20110504000000" dateValid="20110504000000" displayName="Groupement de coopération sanitaire, Etablissement de santé" longDesignation="Groupement de coopération sanitaire - Etablissement de santé" shortDesignation="GCS-ES"/>
            <Concept code="698" codeSystem="1.2.250.1.213.1.6.1.8" dateFin="" dateMaj="19790101000000" dateValid="19790101000000" displayName="Autre établissement relevant de la loi hospitalière" longDesignation="Autre Etablissement Loi Hospitalière" shortDesignation="Autre Etab.Loi Hosp."/>
            <Concept code="699" codeSystem="1.2.250.1.213.1.6.1.8" dateFin="" dateMaj="19790101000000" dateValid="19790101000000" displayName="Entité ayant autorisation" longDesignation="Entité Ayant Autorisation" shortDesignation="Entité Ayant Autor."/>
            <Concept code="700" codeSystem="1.2.250.1.213.1.6.1.8" dateFin="" dateMaj="20241025120000" dateValid="20240726120000" displayName="Maison sport-santé" longDesignation="Maison sport-santé" shortDesignation="Maison sport-santé" descriptionMetier="Catégorie créée à la demande du ROR. A date aucun enregistrement n'est prévu dans FINESS pour cette catégorie"/>
            <Concept code="701" codeSystem="1.2.250.1.213.1.6.1.8" dateFin="" dateMaj="20241025120000" dateValid="20241025120000" displayName="Maison des adolescents (MDA)" longDesignation="Maison des adolescents (MDA)" shortDesignation="MDA" descriptionMetier="Catégorie créée à la demande du ROR. A date aucun enregistrement n'est prévu dans FINESS pour cette catégorie"/>
            <Concept code="702" codeSystem="1.2.250.1.213.1.6.1.8" dateFin="" dateMaj="20241025120000" dateValid="20241025120000" displayName="Point Accueil Ecoute Jeunes (PAEJ)" longDesignation="Point Accueil Ecoute Jeunes (PAEJ)" shortDesignation="PAEJ" descriptionMetier="Catégorie créée à la demande du ROR. A date aucun enregistrement n'est prévu dans FINESS pour cette catégorie"/>
        </ConceptList>
    </ValueSet>
</RetrieveValueSetResponse>
