<?xml version="1.0" encoding="UTF-8" standalone="no"?>
<RetrieveValueSetResponse xmlns="urn:ihe:iti:svs:2008" xmlns:xsi="http://www.w3.org/2001/XMLSchema-instance">
    <ValueSet dateFin="" dateMaj="20240927120000" dateValid="20240927120000" description="Sources d'information possible concernant l'installation de l'activité sociale du RASS" displayName="JDV_J261-SourceInformationInstallation-RASS.tabs" id="1.2.250.1.213.1.6.1.285" typeFichier="JDV" urlFichier="https://mos.esante.gouv.fr/NOS/JDV_J261-SourceInformationInstallation-RASS">
        <ConceptList>
            <Concept code="V" codeSystem="1.2.250.1.213.1.6.1.208" displayName="Visite de conformité"/>
            <Concept code="E" codeSystem="1.2.250.1.213.1.6.1.208" displayName="Enquête statistique"/>
            <Concept code="I" codeSystem="1.2.250.1.213.1.6.1.208" displayName="Interrogation de l'ET"/>
            <Concept code="D" codeSystem="1.2.250.1.213.1.6.1.208" displayName="Document de tarification"/>
            <Concept code="S" codeSystem="1.2.250.1.213.1.6.1.208" displayName="Inspection"/>
            <Concept code="C" codeSystem="1.2.250.1.213.1.6.1.208" displayName="Convention"/>
            <Concept code="L" codeSystem="1.2.250.1.213.1.6.1.208" displayName="Labellisation"/>
            <Concept code="A" codeSystem="1.2.250.1.213.1.6.1.208" displayName="Autre"/>
            <Concept code="R" codeSystem="1.2.250.1.213.1.6.1.208" displayName="Arrêté"/>
        </ConceptList>
    </ValueSet>
</RetrieveValueSetResponse>
