{
  "resourceType" : "CodeSystem",
  "id" : "TRE-R233-TypeFermetureEG",
  "text" : {
    "status" : "generated",
    "div" : "<div xmlns=\"http://www.w3.org/1999/xhtml\"><p class=\"res-header-id\"><b>Generated Narrative: CodeSystem TRE-R233-TypeFermetureEG</b></p><a name=\"TRE-R233-TypeFermetureEG\"> </a><a name=\"hcTRE-R233-TypeFermetureEG\"> </a><a name=\"TRE-R233-TypeFermetureEG-en-US\"> </a><p><b>Properties</b></p><p><b>This code system defines the following properties for its concepts</b></p><table class=\"grid\"><tr><td><b>Name</b></td><td><b>Code</b></td><td><b>Type</b></td><td><b>Description</b></td></tr><tr><td>dateValid</td><td>dateValid</td><td>dateTime</td><td>date de validité d'un code concept</td></tr><tr><td>dateMaj</td><td>dateMaj</td><td>dateTime</td><td>Date de mise à jour d'un code concept</td></tr><tr><td>dateFin</td><td>dateFin</td><td>dateTime</td><td>Date de fin d'exploitation d'un code concept</td></tr></table><p><b>Concepts</b></p><p>This  code system <code>https://mos.esante.gouv.fr/NOS/TRE_R233-TypeFermetureEG/FHIR/TRE-R233-TypeFermetureEG</code> defines the following codes:</p><table class=\"codes\"><tr><td style=\"white-space:nowrap\"><b>Code</b></td><td><b>Display</b></td><td><b>dateValid</b></td><td><b>dateMaj</b></td><td><b>dateFin</b></td></tr><tr><td style=\"white-space:nowrap\">CHP<a name=\"TRE-R233-TypeFermetureEG-CHP\"> </a></td><td>Sortie du champ FINESS</td><td>2017-07-07T10:00:00+01:00</td><td>2019-01-25T12:00:00+01:00</td><td>2019-01-25T12:00:00+01:00</td></tr><tr><td style=\"white-space:nowrap\">DEF<a name=\"TRE-R233-TypeFermetureEG-DEF\"> </a></td><td>Définitive</td><td>2017-07-07T10:00:00+01:00</td><td>2019-01-25T12:00:00+01:00</td><td>2019-01-25T12:00:00+01:00</td></tr><tr><td style=\"white-space:nowrap\">EML<a name=\"TRE-R233-TypeFermetureEG-EML\"> </a></td><td>Ancienne autorisation fonctionnement EML</td><td>2017-07-07T10:00:00+01:00</td><td>2019-01-25T12:00:00+01:00</td><td>2019-01-25T12:00:00+01:00</td></tr><tr><td style=\"white-space:nowrap\">ERR<a name=\"TRE-R233-TypeFermetureEG-ERR\"> </a></td><td>Erreur</td><td>2017-07-07T10:00:00+01:00</td><td>2019-01-25T12:00:00+01:00</td><td>2019-01-25T12:00:00+01:00</td></tr><tr><td style=\"white-space:nowrap\">PRO<a name=\"TRE-R233-TypeFermetureEG-PRO\"> </a></td><td>Provisoire</td><td>2017-07-07T10:00:00+01:00</td><td>2019-01-25T12:00:00+01:00</td><td>2019-01-25T12:00:00+01:00</td></tr></table></div>"
  },
  "extension" : [{
    "url" : "http://hl7.org/fhir/StructureDefinition/resource-effectivePeriod",
    "valuePeriod" : {
      "start" : "2017-07-07T10:00:00+01:00",
      "end" : "2019-01-25T12:00:00+01:00"
    }
  }],
  "url" : "https://mos.esante.gouv.fr/NOS/TRE_R233-TypeFermetureEG/FHIR/TRE-R233-TypeFermetureEG",
  "identifier" : [{
    "value" : "urn:oid:1.2.250.1.213.1.6.1.121"
  }],
  "version" : "1.5.0",
  "name" : "TRE_R233-TypeFermetureEG",
  "status" : "retired",
  "date" : "2023-12-15T12:00:00+01:00",
  "publisher" : "ANS",
  "contact" : [{
    "name" : "ANS",
    "telecom" : [{
      "system" : "url",
      "value" : "https://esante.gouv.fr"
    }]
  }],
  "description" : "Type de fermeture de l'entité géographique FINESS",
  "content" : "complete",
  "property" : [{
    "code" : "dateValid",
    "description" : "date de validité d'un code concept",
    "type" : "dateTime"
  },
  {
    "code" : "dateMaj",
    "description" : "Date de mise à jour d'un code concept",
    "type" : "dateTime"
  },
  {
    "code" : "dateFin",
    "description" : "Date de fin d'exploitation d'un code concept",
    "type" : "dateTime"
  }],
  "concept" : [{
    "code" : "CHP",
    "display" : "Sortie du champ FINESS",
    "designation" : [{
      "use" : {
        "code" : "LibelleCourt"
      },
      "value" : "Sortie du champ FINESS"
    },
    {
      "use" : {
        "code" : "LibelleAdapte"
      },
      "value" : "Sortie du champ FINESS"
    }],
    "property" : [{
      "code" : "dateValid",
      "valueDateTime" : "2017-07-07T10:00:00+01:00"
    },
    {
      "code" : "dateFin",
      "valueDateTime" : "2019-01-25T12:00:00+01:00"
    },
    {
      "code" : "dateMaj",
      "valueDateTime" : "2019-01-25T12:00:00+01:00"
    }]
  },
  {
    "code" : "DEF",
    "display" : "Définitive",
    "designation" : [{
      "use" : {
        "code" : "LibelleCourt"
      },
      "value" : "Définitive"
    },
    {
      "use" : {
        "code" : "LibelleAdapte"
      },
      "value" : "Définitive"
    }],
    "property" : [{
      "code" : "dateValid",
      "valueDateTime" : "2017-07-07T10:00:00+01:00"
    },
    {
      "code" : "dateFin",
      "valueDateTime" : "2019-01-25T12:00:00+01:00"
    },
    {
      "code" : "dateMaj",
      "valueDateTime" : "2019-01-25T12:00:00+01:00"
    }]
  },
  {
    "code" : "EML",
    "display" : "Ancienne autorisation fonctionnement EML",
    "designation" : [{
      "use" : {
        "code" : "LibelleCourt"
      },
      "value" : "Anc autor fonct EML"
    },
    {
      "use" : {
        "code" : "LibelleAdapte"
      },
      "value" : "Ancienne autorisation fonctionnement EML"
    }],
    "property" : [{
      "code" : "dateValid",
      "valueDateTime" : "2017-07-07T10:00:00+01:00"
    },
    {
      "code" : "dateFin",
      "valueDateTime" : "2019-01-25T12:00:00+01:00"
    },
    {
      "code" : "dateMaj",
      "valueDateTime" : "2019-01-25T12:00:00+01:00"
    }]
  },
  {
    "code" : "ERR",
    "display" : "Erreur",
    "designation" : [{
      "use" : {
        "code" : "LibelleCourt"
      },
      "value" : "Erreur"
    },
    {
      "use" : {
        "code" : "LibelleAdapte"
      },
      "value" : "Erreur"
    }],
    "property" : [{
      "code" : "dateValid",
      "valueDateTime" : "2017-07-07T10:00:00+01:00"
    },
    {
      "code" : "dateFin",
      "valueDateTime" : "2019-01-25T12:00:00+01:00"
    },
    {
      "code" : "dateMaj",
      "valueDateTime" : "2019-01-25T12:00:00+01:00"
    }]
  },
  {
    "code" : "PRO",
    "display" : "Provisoire",
    "designation" : [{
      "use" : {
        "code" : "LibelleCourt"
      },
      "value" : "Provisoire"
    },
    {
      "use" : {
        "code" : "LibelleAdapte"
      },
      "value" : "Provisoire"
    }],
    "property" : [{
      "code" : "dateValid",
      "valueDateTime" : "2017-07-07T10:00:00+01:00"
    },
    {
      "code" : "dateFin",
      "valueDateTime" : "2019-01-25T12:00:00+01:00"
    },
    {
      "code" : "dateMaj",
      "valueDateTime" : "2019-01-25T12:00:00+01:00"
    }]
  }]
}