{
  "resourceType" : "CodeSystem",
  "id" : "TRE-R96-AutreFonctionSanitaire",
  "text" : {
    "status" : "generated",
    "div" : "<div xmlns=\"http://www.w3.org/1999/xhtml\"><p class=\"res-header-id\"><b>Generated Narrative: CodeSystem TRE-R96-AutreFonctionSanitaire</b></p><a name=\"TRE-R96-AutreFonctionSanitaire\"> </a><a name=\"hcTRE-R96-AutreFonctionSanitaire\"> </a><a name=\"TRE-R96-AutreFonctionSanitaire-en-US\"> </a><p><b>Properties</b></p><p><b>This code system defines the following properties for its concepts</b></p><table class=\"grid\"><tr><td><b>Name</b></td><td><b>Code</b></td><td><b>Type</b></td><td><b>Description</b></td></tr><tr><td>dateValid</td><td>dateValid</td><td>dateTime</td><td>date de validité d'un code concept</td></tr><tr><td>dateMaj</td><td>dateMaj</td><td>dateTime</td><td>Date de mise à jour d'un code concept</td></tr><tr><td>dateFin</td><td>dateFin</td><td>dateTime</td><td>Date de fin d'exploitation d'un code concept</td></tr></table><p><b>Concepts</b></p><p>This  code system <code>https://mos.esante.gouv.fr/NOS/TRE_R96-AutreFonctionSanitaire/FHIR/TRE-R96-AutreFonctionSanitaire</code> defines the following codes:</p><table class=\"codes\"><tr><td style=\"white-space:nowrap\"><b>Code</b></td><td><b>Display</b></td><td><b>dateValid</b></td><td><b>dateMaj</b></td><td><b>dateFin</b></td></tr><tr><td style=\"white-space:nowrap\">400<a name=\"TRE-R96-AutreFonctionSanitaire-400\"> </a></td><td>Aide-soignant</td><td>2017-10-13T12:00:00+01:00</td><td>2018-10-26T12:00:00+01:00</td><td>2018-10-26T12:00:00+01:00</td></tr><tr><td style=\"white-space:nowrap\">401<a name=\"TRE-R96-AutreFonctionSanitaire-401\"> </a></td><td>Auxiliaire de puériculture</td><td>2017-10-13T12:00:00+01:00</td><td>2018-10-26T12:00:00+01:00</td><td>2018-10-26T12:00:00+01:00</td></tr><tr><td style=\"white-space:nowrap\">402<a name=\"TRE-R96-AutreFonctionSanitaire-402\"> </a></td><td>Préparateur en pharmacie hospitalière</td><td>2017-10-13T12:00:00+01:00</td><td>2018-10-26T12:00:00+01:00</td><td>2018-10-26T12:00:00+01:00</td></tr><tr><td style=\"white-space:nowrap\">403<a name=\"TRE-R96-AutreFonctionSanitaire-403\"> </a></td><td>Préparateur en pharmacie (officine)</td><td>2017-10-13T12:00:00+01:00</td><td>2018-10-26T12:00:00+01:00</td><td>2018-10-26T12:00:00+01:00</td></tr><tr><td style=\"white-space:nowrap\">404<a name=\"TRE-R96-AutreFonctionSanitaire-404\"> </a></td><td>Conseiller en génétique</td><td>2017-10-13T12:00:00+01:00</td><td>2019-03-29T12:00:00+01:00</td><td>2019-03-29T12:00:00+01:00</td></tr><tr><td style=\"white-space:nowrap\">405<a name=\"TRE-R96-AutreFonctionSanitaire-405\"> </a></td><td>Radiophysicien</td><td>2017-10-13T12:00:00+01:00</td><td>2019-04-26T12:00:00+01:00</td><td>2019-04-26T12:00:00+01:00</td></tr><tr><td style=\"white-space:nowrap\">406<a name=\"TRE-R96-AutreFonctionSanitaire-406\"> </a></td><td>Assistant dentaire</td><td>2017-10-13T12:00:00+01:00</td><td>2018-10-26T12:00:00+01:00</td><td>2018-10-26T12:00:00+01:00</td></tr><tr><td style=\"white-space:nowrap\">407<a name=\"TRE-R96-AutreFonctionSanitaire-407\"> </a></td><td>Tatoueur</td><td>2017-10-13T12:00:00+01:00</td><td>2017-10-13T12:00:00+01:00</td><td/></tr><tr><td style=\"white-space:nowrap\">408<a name=\"TRE-R96-AutreFonctionSanitaire-408\"> </a></td><td>Perceur corporel</td><td>2017-10-13T12:00:00+01:00</td><td>2017-10-13T12:00:00+01:00</td><td/></tr><tr><td style=\"white-space:nowrap\">409<a name=\"TRE-R96-AutreFonctionSanitaire-409\"> </a></td><td>Maquilleur permanent</td><td>2017-10-13T12:00:00+01:00</td><td>2019-03-29T12:00:00+01:00</td><td/></tr></table></div>"
  },
  "extension" : [{
    "url" : "http://hl7.org/fhir/StructureDefinition/resource-effectivePeriod",
    "valuePeriod" : {
      "start" : "2017-10-13T12:00:00+01:00"
    }
  }],
  "url" : "https://mos.esante.gouv.fr/NOS/TRE_R96-AutreFonctionSanitaire/FHIR/TRE-R96-AutreFonctionSanitaire",
  "identifier" : [{
    "value" : "urn:oid:1.2.250.1.213.1.6.1.110"
  }],
  "version" : "1.5.0",
  "name" : "TRE_R96-AutreFonctionSanitaire",
  "status" : "active",
  "date" : "2023-12-15T12:00:00+01:00",
  "publisher" : "ANS",
  "contact" : [{
    "name" : "ANS",
    "telecom" : [{
      "system" : "url",
      "value" : "https://esante.gouv.fr"
    }]
  }],
  "description" : "Autres fonctions du domaine sanitaire",
  "content" : "complete",
  "property" : [{
    "code" : "dateValid",
    "description" : "date de validité d'un code concept",
    "type" : "dateTime"
  },
  {
    "code" : "dateMaj",
    "description" : "Date de mise à jour d'un code concept",
    "type" : "dateTime"
  },
  {
    "code" : "dateFin",
    "description" : "Date de fin d'exploitation d'un code concept",
    "type" : "dateTime"
  }],
  "concept" : [{
    "code" : "400",
    "display" : "Aide-soignant",
    "designation" : [{
      "use" : {
        "code" : "LibelleCourt"
      },
      "value" : "Aide-soignant"
    },
    {
      "use" : {
        "code" : "LibelleAdapte"
      },
      "value" : "Aide-soignant"
    }],
    "property" : [{
      "code" : "dateValid",
      "valueDateTime" : "2017-10-13T12:00:00+01:00"
    },
    {
      "code" : "dateFin",
      "valueDateTime" : "2018-10-26T12:00:00+01:00"
    },
    {
      "code" : "dateMaj",
      "valueDateTime" : "2018-10-26T12:00:00+01:00"
    }]
  },
  {
    "code" : "401",
    "display" : "Auxiliaire de puériculture",
    "designation" : [{
      "use" : {
        "code" : "LibelleCourt"
      },
      "value" : "Auxiliaire de puériculture"
    },
    {
      "use" : {
        "code" : "LibelleAdapte"
      },
      "value" : "Auxiliaire de puériculture"
    }],
    "property" : [{
      "code" : "dateValid",
      "valueDateTime" : "2017-10-13T12:00:00+01:00"
    },
    {
      "code" : "dateFin",
      "valueDateTime" : "2018-10-26T12:00:00+01:00"
    },
    {
      "code" : "dateMaj",
      "valueDateTime" : "2018-10-26T12:00:00+01:00"
    }]
  },
  {
    "code" : "402",
    "display" : "Préparateur en pharmacie hospitalière",
    "designation" : [{
      "use" : {
        "code" : "LibelleCourt"
      },
      "value" : "Prép en pharmacie (hôpital)"
    },
    {
      "use" : {
        "code" : "LibelleAdapte"
      },
      "value" : "Préparateur en pharmacie hospitalière"
    }],
    "property" : [{
      "code" : "dateValid",
      "valueDateTime" : "2017-10-13T12:00:00+01:00"
    },
    {
      "code" : "dateFin",
      "valueDateTime" : "2018-10-26T12:00:00+01:00"
    },
    {
      "code" : "dateMaj",
      "valueDateTime" : "2018-10-26T12:00:00+01:00"
    }]
  },
  {
    "code" : "403",
    "display" : "Préparateur en pharmacie (officine)",
    "designation" : [{
      "use" : {
        "code" : "LibelleCourt"
      },
      "value" : "Prép en pharmacie (officine)"
    },
    {
      "use" : {
        "code" : "LibelleAdapte"
      },
      "value" : "Préparateur en pharmacie (officine)"
    }],
    "property" : [{
      "code" : "dateValid",
      "valueDateTime" : "2017-10-13T12:00:00+01:00"
    },
    {
      "code" : "dateFin",
      "valueDateTime" : "2018-10-26T12:00:00+01:00"
    },
    {
      "code" : "dateMaj",
      "valueDateTime" : "2018-10-26T12:00:00+01:00"
    }]
  },
  {
    "code" : "404",
    "display" : "Conseiller en génétique",
    "designation" : [{
      "use" : {
        "code" : "LibelleCourt"
      },
      "value" : "Conseiller en génétique"
    },
    {
      "use" : {
        "code" : "LibelleAdapte"
      },
      "value" : "Conseiller en génétique"
    }],
    "property" : [{
      "code" : "dateValid",
      "valueDateTime" : "2017-10-13T12:00:00+01:00"
    },
    {
      "code" : "dateFin",
      "valueDateTime" : "2019-03-29T12:00:00+01:00"
    },
    {
      "code" : "dateMaj",
      "valueDateTime" : "2019-03-29T12:00:00+01:00"
    }]
  },
  {
    "code" : "405",
    "display" : "Radiophysicien",
    "designation" : [{
      "use" : {
        "code" : "LibelleCourt"
      },
      "value" : "Radiophysicien"
    },
    {
      "use" : {
        "code" : "LibelleAdapte"
      },
      "value" : "Radiophysicien"
    }],
    "property" : [{
      "code" : "dateValid",
      "valueDateTime" : "2017-10-13T12:00:00+01:00"
    },
    {
      "code" : "dateFin",
      "valueDateTime" : "2019-04-26T12:00:00+01:00"
    },
    {
      "code" : "dateMaj",
      "valueDateTime" : "2019-04-26T12:00:00+01:00"
    }]
  },
  {
    "code" : "406",
    "display" : "Assistant dentaire",
    "designation" : [{
      "use" : {
        "code" : "LibelleCourt"
      },
      "value" : "Assistant dentaire"
    },
    {
      "use" : {
        "code" : "LibelleAdapte"
      },
      "value" : "Assistant dentaire"
    }],
    "property" : [{
      "code" : "dateValid",
      "valueDateTime" : "2017-10-13T12:00:00+01:00"
    },
    {
      "code" : "dateFin",
      "valueDateTime" : "2018-10-26T12:00:00+01:00"
    },
    {
      "code" : "dateMaj",
      "valueDateTime" : "2018-10-26T12:00:00+01:00"
    }]
  },
  {
    "code" : "407",
    "display" : "Tatoueur",
    "designation" : [{
      "use" : {
        "code" : "LibelleCourt"
      },
      "value" : "Tatoueur"
    },
    {
      "use" : {
        "code" : "LibelleAdapte"
      },
      "value" : "Tatoueur"
    }],
    "property" : [{
      "code" : "dateValid",
      "valueDateTime" : "2017-10-13T12:00:00+01:00"
    },
    {
      "code" : "dateMaj",
      "valueDateTime" : "2017-10-13T12:00:00+01:00"
    }]
  },
  {
    "code" : "408",
    "display" : "Perceur corporel",
    "designation" : [{
      "use" : {
        "code" : "LibelleCourt"
      },
      "value" : "Perceur corporel"
    },
    {
      "use" : {
        "code" : "LibelleAdapte"
      },
      "value" : "Perceur corporel"
    }],
    "property" : [{
      "code" : "dateValid",
      "valueDateTime" : "2017-10-13T12:00:00+01:00"
    },
    {
      "code" : "dateMaj",
      "valueDateTime" : "2017-10-13T12:00:00+01:00"
    }]
  },
  {
    "code" : "409",
    "display" : "Maquilleur permanent",
    "designation" : [{
      "use" : {
        "code" : "LibelleCourt"
      },
      "value" : "Maquilleur permanent"
    },
    {
      "use" : {
        "code" : "LibelleAdapte"
      },
      "value" : "Maquilleur permanent"
    }],
    "property" : [{
      "code" : "dateValid",
      "valueDateTime" : "2017-10-13T12:00:00+01:00"
    },
    {
      "code" : "dateMaj",
      "valueDateTime" : "2019-03-29T12:00:00+01:00"
    }]
  }]
}