{
  "resourceType" : "CodeSystem",
  "id" : "TRE-R259-HL7ParticipationFunction",
  "text" : {
    "status" : "generated",
    "div" : "<div xmlns=\"http://www.w3.org/1999/xhtml\"><p class=\"res-header-id\"><b>Generated Narrative: CodeSystem TRE-R259-HL7ParticipationFunction</b></p><a name=\"TRE-R259-HL7ParticipationFunction\"> </a><a name=\"hcTRE-R259-HL7ParticipationFunction\"> </a><a name=\"TRE-R259-HL7ParticipationFunction-en-US\"> </a><p><b>Properties</b></p><p><b>This code system defines the following properties for its concepts</b></p><table class=\"grid\"><tr><td><b>Name</b></td><td><b>Code</b></td><td><b>Type</b></td><td><b>Description</b></td></tr><tr><td>dateValid</td><td>dateValid</td><td>dateTime</td><td>date de validité d'un code concept</td></tr><tr><td>dateMaj</td><td>dateMaj</td><td>dateTime</td><td>Date de mise à jour d'un code concept</td></tr><tr><td>dateFin</td><td>dateFin</td><td>dateTime</td><td>Date de fin d'exploitation d'un code concept</td></tr></table><p><b>Concepts</b></p><p>This  code system <code>https://mos.esante.gouv.fr/NOS/TRE_R259-HL7ParticipationFunction/FHIR/TRE-R259-HL7ParticipationFunction</code> defines the following codes:</p><table class=\"codes\"><tr><td style=\"white-space:nowrap\"><b>Code</b></td><td><b>Display</b></td><td><b>dateValid</b></td><td><b>dateMaj</b></td></tr><tr><td style=\"white-space:nowrap\">ADMPHYS<a name=\"TRE-R259-HL7ParticipationFunction-ADMPHYS\"> </a></td><td>Responsable de l'admission</td><td>2018-03-30T12:00:00+01:00</td><td>2018-03-30T12:00:00+01:00</td></tr><tr><td style=\"white-space:nowrap\">ATTPHYS<a name=\"TRE-R259-HL7ParticipationFunction-ATTPHYS\"> </a></td><td>Référent - Responsable du patient dans la structure de soins</td><td>2018-03-30T12:00:00+01:00</td><td>2018-03-30T12:00:00+01:00</td></tr><tr><td style=\"white-space:nowrap\">DISPHYS<a name=\"TRE-R259-HL7ParticipationFunction-DISPHYS\"> </a></td><td>Responsable de la sortie</td><td>2018-03-30T12:00:00+01:00</td><td>2018-03-30T12:00:00+01:00</td></tr><tr><td style=\"white-space:nowrap\">PCP<a name=\"TRE-R259-HL7ParticipationFunction-PCP\"> </a></td><td>Médecin traitant</td><td>2018-03-30T12:00:00+01:00</td><td>2018-03-30T12:00:00+01:00</td></tr></table></div>"
  },
  "extension" : [{
    "url" : "http://hl7.org/fhir/StructureDefinition/resource-effectivePeriod",
    "valuePeriod" : {
      "start" : "2018-03-30T12:00:00+01:00"
    }
  }],
  "url" : "https://mos.esante.gouv.fr/NOS/TRE_R259-HL7ParticipationFunction/FHIR/TRE-R259-HL7ParticipationFunction",
  "identifier" : [{
    "value" : "urn:oid:2.16.840.1.113883.5.88"
  }],
  "version" : "1.5.0",
  "name" : "TRE_R259-HL7ParticipationFunction",
  "status" : "active",
  "date" : "2023-12-15T12:00:00+01:00",
  "publisher" : "ANS",
  "contact" : [{
    "name" : "ANS",
    "telecom" : [{
      "system" : "url",
      "value" : "https://esante.gouv.fr"
    }]
  }],
  "description" : "Rôles fonctionnels HL7",
  "content" : "complete",
  "property" : [{
    "code" : "dateValid",
    "description" : "date de validité d'un code concept",
    "type" : "dateTime"
  },
  {
    "code" : "dateMaj",
    "description" : "Date de mise à jour d'un code concept",
    "type" : "dateTime"
  },
  {
    "code" : "dateFin",
    "description" : "Date de fin d'exploitation d'un code concept",
    "type" : "dateTime"
  }],
  "concept" : [{
    "code" : "ADMPHYS",
    "display" : "Responsable de l'admission",
    "designation" : [{
      "use" : {
        "code" : "LibelleCourt"
      },
      "value" : "Responsable de l'admission"
    },
    {
      "use" : {
        "code" : "LibelleAdapte"
      },
      "value" : "Responsable de l'admission"
    }],
    "property" : [{
      "code" : "dateValid",
      "valueDateTime" : "2018-03-30T12:00:00+01:00"
    },
    {
      "code" : "dateMaj",
      "valueDateTime" : "2018-03-30T12:00:00+01:00"
    }]
  },
  {
    "code" : "ATTPHYS",
    "display" : "Référent - Responsable du patient dans la structure de soins",
    "designation" : [{
      "use" : {
        "code" : "LibelleCourt"
      },
      "value" : "Réf- Resp_patient_STSoins"
    },
    {
      "use" : {
        "code" : "LibelleAdapte"
      },
      "value" : "Référent - Responsable du patient dans la structure de soins"
    }],
    "property" : [{
      "code" : "dateValid",
      "valueDateTime" : "2018-03-30T12:00:00+01:00"
    },
    {
      "code" : "dateMaj",
      "valueDateTime" : "2018-03-30T12:00:00+01:00"
    }]
  },
  {
    "code" : "DISPHYS",
    "display" : "Responsable de la sortie",
    "designation" : [{
      "use" : {
        "code" : "LibelleCourt"
      },
      "value" : "Responsable de la sortie"
    },
    {
      "use" : {
        "code" : "LibelleAdapte"
      },
      "value" : "Responsable de la sortie"
    }],
    "property" : [{
      "code" : "dateValid",
      "valueDateTime" : "2018-03-30T12:00:00+01:00"
    },
    {
      "code" : "dateMaj",
      "valueDateTime" : "2018-03-30T12:00:00+01:00"
    }]
  },
  {
    "code" : "PCP",
    "display" : "Médecin traitant",
    "designation" : [{
      "use" : {
        "code" : "LibelleCourt"
      },
      "value" : "Médecin traitant"
    },
    {
      "use" : {
        "code" : "LibelleAdapte"
      },
      "value" : "Médecin traitant"
    }],
    "property" : [{
      "code" : "dateValid",
      "valueDateTime" : "2018-03-30T12:00:00+01:00"
    },
    {
      "code" : "dateMaj",
      "valueDateTime" : "2018-03-30T12:00:00+01:00"
    }]
  }]
}