{
  "resourceType": "CodeSystem",
  "id": "dce7b02f-ca68-4f9e-a10c-6b42f5877e3b",
  "meta": {
    "versionId": "1",
    "lastUpdated": "2022-09-08T16:09:35.210+00:00"
  },
  "extension": [ {
    "url": "http://hl7.org/fhir/StructureDefinition/resource-effectivePeriod",
    "valuePeriod": {
      "start": "2013-06-28T00:00:00+02:00"
    }
  } ],
  "url": "https://mos.esante.gouv.fr/NOS/TRE_R45-FonctionQualifiee",
  "identifier": [ {
    "value": "urn:oid:1.2.250.1.213.2.35"
  } ],
  "version": "20200424120000",
  "name": "TRE_R45-FonctionQualifiee",
  "status": "active",
  "date": "2013-06-28T00:00:00+02:00",
  "description": "Fonction qualifiée",
  "content": "complete",
  "property": [ {
    "code": "dateValid",
    "description": "date de validité d'un code concept",
    "type": "dateTime"
  }, {
    "code": "dateMaj",
    "description": "date de mise à jours d'un code concept",
    "type": "dateTime"
  }, {
    "code": "dateFin",
    "description": "date de fin d'un code concept",
    "type": "dateTime"
  } ],
  "concept": [ {
    "code": "FQ02",
    "display": "Expérience pratique art R.5124-16 du CSP Exploitant (FQ)",
    "designation": [ {
      "use": {
        "code": "LibelleCourt"
      },
      "value": "Expér prat R.5124-16 Exploit"
    }, {
      "use": {
        "system": "http://data.esante.gouv.fr/nos/1.2.250.1.213.2.35",
        "code": "LibelleAdapte"
      },
      "value": "Expérience pratique art R.5124-16 du CSP Exploitant (FQ)"
    } ],
    "property": [ {
      "code": "dateValid",
      "valueDateTime": "2007-07-26T00:00:00+02:00"
    }, {
      "code": "dateMaj",
      "valueDateTime": "2016-09-01T00:00:00+02:00"
    } ]
  }, {
    "code": "FQ05",
    "display": "Expérience pratique art R.5141-129 du CSP Autovaccins (FQ)",
    "designation": [ {
      "use": {
        "code": "LibelleCourt"
      },
      "value": "Expér prat R.5141-129 Autovac"
    }, {
      "use": {
        "system": "http://data.esante.gouv.fr/nos/1.2.250.1.213.2.35",
        "code": "LibelleAdapte"
      },
      "value": "Expérience pratique art R.5141-129 du CSP Autovaccins (FQ)"
    } ],
    "property": [ {
      "code": "dateValid",
      "valueDateTime": "2007-07-26T00:00:00+02:00"
    }, {
      "code": "dateMaj",
      "valueDateTime": "2016-09-01T00:00:00+02:00"
    } ]
  }, {
    "code": "FQ03",
    "display": "Expérience pratique art R.5124-16 du CSP Thérapie cellulaire (FQ)",
    "designation": [ {
      "use": {
        "code": "LibelleAdapte"
      },
      "value": "Expérience pratique art R.5124-16 du CSP Thérapie cellulaire (FQ)"
    }, {
      "use": {
        "code": "LibelleCourt"
      },
      "value": "Expér prat R.5124-16 Thér cel"
    } ],
    "property": [ {
      "code": "dateMaj",
      "valueDateTime": "2016-09-01T00:00:00+02:00"
    }, {
      "code": "dateValid",
      "valueDateTime": "2007-07-26T00:00:00+02:00"
    } ]
  }, {
    "code": "FQ01",
    "display": "Expérience pratique art R.5124-16 du CSP Fabricant (FQ)",
    "designation": [ {
      "use": {
        "code": "LibelleCourt"
      },
      "value": "Expér prat R.5124-16 Fabricant"
    }, {
      "use": {
        "code": "LibelleAdapte"
      },
      "value": "Expérience pratique art R.5124-16 du CSP Fabricant (FQ)"
    } ],
    "property": [ {
      "code": "dateValid",
      "valueDateTime": "2007-07-26T00:00:00+02:00"
    }, {
      "code": "dateMaj",
      "valueDateTime": "2016-09-01T00:00:00+02:00"
    } ]
  }, {
    "code": "FQ04",
    "display": "Expérience pratique art R.5124-18 du CSP Pharmacie (FQ)",
    "designation": [ {
      "use": {
        "code": "LibelleAdapte"
      },
      "value": "Expérience pratique art R.5124-18 du CSP Pharmacie (FQ)"
    }, {
      "use": {
        "system": "http://data.esante.gouv.fr/nos/1.2.250.1.213.2.35",
        "code": "LibelleCourt"
      },
      "value": "Expér prat R.5124-18 Pharmacie"
    } ],
    "property": [ {
      "code": "dateMaj",
      "valueDateTime": "2016-09-01T00:00:00+02:00"
    }, {
      "code": "dateValid",
      "valueDateTime": "2007-07-26T00:00:00+02:00"
    } ]
  } ]
}