{
  "resourceType": "CodeSystem",
  "id": "c4655a12-e92e-4d7b-b8c1-975bb1519a03",
  "meta": {
    "versionId": "1",
    "lastUpdated": "2022-09-08T16:10:02.253+00:00"
  },
  "extension": [ {
    "url": "http://hl7.org/fhir/StructureDefinition/resource-effectivePeriod",
    "valuePeriod": {
      "start": "2016-09-01T00:00:00+02:00"
    }
  } ],
  "url": "https://mos.esante.gouv.fr/NOS/TRE_A10-NomenclatureURN",
  "identifier": [ {
    "value": "urn:oid:URN"
  } ],
  "version": "20200424120000",
  "name": "TRE_A10-NomenclatureURN",
  "status": "active",
  "date": "2016-09-01T00:00:00+02:00",
  "description": "Nomenclature identifiée par URN",
  "content": "complete",
  "property": [ {
    "code": "dateValid",
    "description": "date de validité d'un code concept",
    "type": "dateTime"
  }, {
    "code": "dateMaj",
    "description": "date de mise à jours d'un code concept",
    "type": "dateTime"
  }, {
    "code": "dateFin",
    "description": "date de fin d'un code concept",
    "type": "dateTime"
  } ],
  "concept": [ {
    "code": "http://www.w3.org/2000/09/xmldsig#",
    "display": "Default signature style",
    "designation": [ {
      "use": {
        "code": "LibelleCourt"
      },
      "value": "Default signature style"
    }, {
      "use": {
        "system": "http://data.esante.gouv.fr/nos/URN",
        "code": "LibelleAdapte"
      },
      "value": "Default signature style"
    } ],
    "property": [ {
      "code": "dateMaj",
      "valueDateTime": "2017-10-13T12:00:00+02:00"
    }, {
      "code": "dateValid",
      "valueDateTime": "2016-09-01T00:00:00+02:00"
    }, {
      "code": "dateFin",
      "valueDateTime": "2017-10-13T12:00:00+02:00"
    } ]
  }, {
    "code": "urn:oid:1.3.6.1.4.1.19376.1.2.1.1.1",
    "display": "Digital Signature",
    "designation": [ {
      "use": {
        "code": "LibelleCourt"
      },
      "value": "Digital Signature"
    }, {
      "use": {
        "code": "LibelleAdapte"
      },
      "value": "Digital Signature"
    } ],
    "property": [ {
      "code": "dateMaj",
      "valueDateTime": "2018-02-28T12:00:00+01:00"
    }, {
      "code": "dateValid",
      "valueDateTime": "2016-09-01T00:00:00+02:00"
    } ]
  } ]
}