{
  "resourceType": "CodeSystem",
  "id": "82ba2185-1057-4e3e-a744-6f18fad8dece",
  "meta": {
    "versionId": "1",
    "lastUpdated": "2022-09-08T16:09:42.155+00:00"
  },
  "extension": [ {
    "url": "http://hl7.org/fhir/StructureDefinition/resource-effectivePeriod",
    "valuePeriod": {
      "start": "2013-04-30T00:00:00+02:00"
    }
  } ],
  "url": "https://mos.esante.gouv.fr/NOS/TRE_R67-TypeStructure-EJ-EG",
  "identifier": [ {
    "value": "urn:oid:1.2.250.1.213.1.6.1.62"
  } ],
  "version": "20200424120000",
  "name": "TRE_R67-TypeStructure-EJ-EG",
  "status": "active",
  "date": "2013-04-30T00:00:00+02:00",
  "description": "Type de structure",
  "content": "complete",
  "property": [ {
    "code": "dateValid",
    "description": "date de validité d'un code concept",
    "type": "dateTime"
  }, {
    "code": "dateMaj",
    "description": "date de mise à jours d'un code concept",
    "type": "dateTime"
  }, {
    "code": "dateFin",
    "description": "date de fin d'un code concept",
    "type": "dateTime"
  } ],
  "concept": [ {
    "code": "EG",
    "display": "Etablissement géographique",
    "designation": [ {
      "use": {
        "code": "LibelleCourt"
      },
      "value": "Etablissement géographique"
    }, {
      "use": {
        "code": "LibelleAdapte"
      },
      "value": "Etablissement géographique"
    } ],
    "property": [ {
      "code": "dateMaj",
      "valueDateTime": "2013-04-30T00:00:00+02:00"
    }, {
      "code": "dateValid",
      "valueDateTime": "2013-04-30T00:00:00+02:00"
    } ]
  }, {
    "code": "EJ",
    "display": "Entité juridique",
    "designation": [ {
      "use": {
        "system": "http://data.esante.gouv.fr/nos/1.2.250.1.213.1.6.1.62",
        "code": "LibelleAdapte"
      },
      "value": "Entité juridique"
    }, {
      "use": {
        "system": "http://data.esante.gouv.fr/nos/1.2.250.1.213.1.6.1.62",
        "code": "LibelleCourt"
      },
      "value": "Entité juridique"
    } ],
    "property": [ {
      "code": "dateValid",
      "valueDateTime": "2013-04-30T00:00:00+02:00"
    }, {
      "code": "dateMaj",
      "valueDateTime": "2013-04-30T00:00:00+02:00"
    } ]
  } ]
}